{
  "type": "collection",
  "entry": [
    {
      "fullUrl": "urn:uuid:432ec178-094d-436f-8652-b99faac06775",
      "resource": {
        "id": "432ec178-094d-436f-8652-b99faac06775",
        "meta": {
          "profile": [
            "http://standardhealthrecord.org/fhir/StructureDefinition/shr-actor-Organization"
          ]
        },
        "type": [
          {
            "coding": [
              {
                "system": "http://hl7.org/fhir/ValueSet/organization-type",
                "code": "prov",
                "display": "Healthcare Provider"
              }
            ],
            "text": "Healthcare Provider"
          }
        ],
        "name": "HEALTHSOUTH BRAINTREE OCC HLTH & RE",
        "resourceType": "Organization"
      }
    },
    {
      "fullUrl": "urn:uuid:c7f974eb-e315-44a1-8d70-61fad4c6c6bd",
      "resource": {
        "id": "c7f974eb-e315-44a1-8d70-61fad4c6c6bd",
        "meta": {
          "profile": [
            "http://standardhealthrecord.org/fhir/StructureDefinition/shr-demographics-PersonOfRecord"
          ]
        },
        "text": {
          "status": "generated",
          "div": "<div xmlns=\"http://www.w3.org/1999/xhtml\">Generated by <a href=\"https://github.com/synthetichealth/synthea\">Synthea</a>. Version identifier: 01d01d675c68502483be0eb37fb293bba5371d7f</div>"
        },
        "extension": [
          {
            "url": "http://hl7.org/fhir/us/core/StructureDefinition/us-core-race",
            "valueCodeableConcept": {
              "coding": [
                {
                  "system": "http://hl7.org/fhir/v3/Race",
                  "code": "2106-3",
                  "display": "White"
                }
              ],
              "text": "race"
            }
          },
          {
            "url": "http://hl7.org/fhir/us/core/StructureDefinition/us-core-ethnicity",
            "valueCodeableConcept": {
              "coding": [
                {
                  "system": "http://hl7.org/fhir/v3/Ethnicity",
                  "code": "2186-5",
                  "display": "Nonhispanic"
                }
              ],
              "text": "ethnicity"
            }
          },
          {
            "url": "http://hl7.org/fhir/StructureDefinition/birthPlace",
            "valueAddress": {
              "city": "Falmouth",
              "state": "MA",
              "country": "US"
            }
          },
          {
            "url": "http://hl7.org/fhir/StructureDefinition/patient-mothersMaidenName",
            "valueString": "Christel237 Hirthe287"
          },
          {
            "url": "http://hl7.org/fhir/us/core/StructureDefinition/us-core-birthsex",
            "valueCode": "M"
          },
          {
            "url": "http://hl7.org/fhir/StructureDefinition/patient-interpreterRequired",
            "valueBoolean": false
          },
          {
            "url": "http://standardhealthrecord.org/fhir/StructureDefinition/shr-actor-FictionalPerson-extension",
            "valueBoolean": true
          },
          {
            "url": "http://standardhealthrecord.org/fhir/StructureDefinition/shr-demographics-FathersName-extension",
            "valueHumanName": {
              "text": "Mohammed690 Heller570"
            }
          },
          {
            "url": "http://standardhealthrecord.org/fhir/StructureDefinition/shr-demographics-SocialSecurityNumber-extension",
            "valueString": "999-45-6977"
          }
        ],
        "identifier": [
          {
            "system": "https://github.com/synthetichealth/synthea",
            "value": "ceb8db9f-258b-49f4-a494-f042eff1cc3a"
          },
          {
            "type": {
              "coding": [
                {
                  "system": "http://hl7.org/fhir/identifier-type",
                  "code": "SB"
                }
              ]
            },
            "system": "http://hl7.org/fhir/sid/us-ssn",
            "value": "999456977"
          },
          {
            "type": {
              "coding": [
                {
                  "system": "http://hl7.org/fhir/v2/0203",
                  "code": "DL"
                }
              ]
            },
            "system": "urn:oid:2.16.840.1.113883.4.3.25",
            "value": "S99939858"
          },
          {
            "type": {
              "coding": [
                {
                  "system": "http://hl7.org/fhir/v2/0203",
                  "code": "PPN"
                }
              ]
            },
            "system": "http://standardhealthrecord.org/fhir/StructureDefinition/passportNumber",
            "value": "X11614401X"
          },
          {
            "type": {
              "coding": [
                {
                  "system": "http://hl7.org/fhir/v2/0203",
                  "code": "MR"
                }
              ]
            },
            "system": "http://hospital.smarthealthit.org",
            "value": "ceb8db9f-258b-49f4-a494-f042eff1cc3a"
          }
        ],
        "name": [
          {
            "use": "official",
            "family": "Heller570",
            "given": [
              "Merlin609"
            ],
            "prefix": [
              "Mr."
            ]
          }
        ],
        "telecom": [
          {
            "system": "phone",
            "value": "1-312-572-6418",
            "use": "home"
          }
        ],
        "gender": "male",
        "birthDate": "1973-06-28",
        "address": [
          {
            "extension": [
              {
                "extension": [
                  {
                    "url": "latitude",
                    "valueDecimal": 42.16491080327638
                  },
                  {
                    "url": "longitude",
                    "valueDecimal": -71.05084755799797
                  }
                ],
                "url": "http://hl7.org/fhir/StructureDefinition/geolocation"
              }
            ],
            "line": [
              "959 Bradtke Keys",
              "Apt. 845"
            ],
            "city": "Randolph",
            "state": "MA",
            "postalCode": "02368",
            "country": "US"
          }
        ],
        "maritalStatus": {
          "coding": [
            {
              "system": "http://hl7.org/fhir/v3/MaritalStatus",
              "code": "M"
            }
          ],
          "text": "M"
        },
        "multipleBirthBoolean": false,
        "communication": [
          {
            "language": {
              "coding": [
                {
                  "system": "http://hl7.org/fhir/ValueSet/languages",
                  "code": "en-US",
                  "display": "English (United States)"
                }
              ]
            }
          }
        ],
        "generalPractitioner": [
          {
            "reference": "urn:uuid:432ec178-094d-436f-8652-b99faac06775"
          }
        ],
        "resourceType": "Patient"
      }
    },
    {
      "fullUrl": "urn:uuid:203a007e-fc81-47bd-a552-d0f2e8aede45",
      "resource": {
        "id": "203a007e-fc81-47bd-a552-d0f2e8aede45",
        "meta": {
          "profile": [
            "http://standardhealthrecord.org/fhir/StructureDefinition/shr-encounter-Encounter"
          ]
        },
        "status": "finished",
        "class": {
          "code": "outpatient"
        },
        "type": [
          {
            "coding": [
              {
                "system": "http://snomed.info/sct",
                "code": "185349003"
              }
            ],
            "text": "Outpatient Encounter"
          }
        ],
        "subject": {
          "reference": "urn:uuid:c7f974eb-e315-44a1-8d70-61fad4c6c6bd"
        },
        "period": {
          "start": "2008-01-03T19:56:24-05:00",
          "end": "2008-01-03T20:56:24-05:00"
        },
        "serviceProvider": {
          "reference": "urn:uuid:432ec178-094d-436f-8652-b99faac06775"
        },
        "resourceType": "Encounter"
      }
    },
    {
      "fullUrl": "urn:uuid:2be7881c-89f2-4f8d-a9df-e2d53701c925",
      "resource": {
        "id": "2be7881c-89f2-4f8d-a9df-e2d53701c925",
        "meta": {
          "profile": [
            "http://standardhealthrecord.org/fhir/StructureDefinition/shr-problem-Problem"
          ]
        },
        "clinicalStatus": "active",
        "verificationStatus": "confirmed",
        "code": {
          "coding": [
            {
              "system": "http://snomed.info/sct",
              "code": "87433001",
              "display": "Pulmonary emphysema (disorder)"
            }
          ],
          "text": "Pulmonary emphysema (disorder)"
        },
        "subject": {
          "reference": "urn:uuid:c7f974eb-e315-44a1-8d70-61fad4c6c6bd"
        },
        "context": {
          "reference": "urn:uuid:203a007e-fc81-47bd-a552-d0f2e8aede45"
        },
        "onsetDateTime": "2006-12-17T02:18:59-05:00",
        "assertedDate": "2006-12-17",
        "resourceType": "Condition"
      }
    },
    {
      "fullUrl": "urn:uuid:8288cd45-58a7-4797-96aa-7088f75149da",
      "resource": {
        "id": "8288cd45-58a7-4797-96aa-7088f75149da",
        "meta": {
          "profile": [
            "http://standardhealthrecord.org/fhir/StructureDefinition/shr-observation-Observation",
            "http://standardhealthrecord.org/fhir/StructureDefinition/shr-vital-VitalSign",
            "http://standardhealthrecord.org/fhir/StructureDefinition/shr-vital-BodyHeight"
          ]
        },
        "status": "final",
        "category": [
          {
            "coding": [
              {
                "system": "http://hl7.org/fhir/observation-category",
                "code": "vital-signs"
              }
            ]
          }
        ],
        "code": {
          "coding": [
            {
              "system": "http://loinc.org",
              "code": "8302-2",
              "display": "Body Height"
            }
          ],
          "text": "Body Height"
        },
        "subject": {
          "reference": "urn:uuid:c7f974eb-e315-44a1-8d70-61fad4c6c6bd"
        },
        "context": {
          "reference": "urn:uuid:203a007e-fc81-47bd-a552-d0f2e8aede45"
        },
        "effectiveDateTime": "2008-01-03T19:56:24-05:00",
        "issued": "2008-01-03T19:56:24-05:00",
        "valueQuantity": {
          "value": 172.77271219700336,
          "unit": "cm",
          "system": "http://unitsofmeasure.org/",
          "code": "cm"
        },
        "resourceType": "Observation"
      }
    },
    {
      "fullUrl": "urn:uuid:4c9d47ce-0067-44b0-a173-3bdf5978a718",
      "resource": {
        "id": "4c9d47ce-0067-44b0-a173-3bdf5978a718",
        "meta": {
          "profile": [
            "http://standardhealthrecord.org/fhir/StructureDefinition/shr-observation-Observation",
            "http://standardhealthrecord.org/fhir/StructureDefinition/shr-vital-VitalSign",
            "http://standardhealthrecord.org/fhir/StructureDefinition/shr-vital-BodyWeight"
          ]
        },
        "status": "final",
        "category": [
          {
            "coding": [
              {
                "system": "http://hl7.org/fhir/observation-category",
                "code": "vital-signs"
              }
            ]
          }
        ],
        "code": {
          "coding": [
            {
              "system": "http://loinc.org",
              "code": "29463-7",
              "display": "Body Weight"
            }
          ],
          "text": "Body Weight"
        },
        "subject": {
          "reference": "urn:uuid:c7f974eb-e315-44a1-8d70-61fad4c6c6bd"
        },
        "context": {
          "reference": "urn:uuid:203a007e-fc81-47bd-a552-d0f2e8aede45"
        },
        "effectiveDateTime": "2008-01-03T19:56:24-05:00",
        "issued": "2008-01-03T19:56:24-05:00",
        "valueQuantity": {
          "value": 122.89501809231247,
          "unit": "kg",
          "system": "http://unitsofmeasure.org/",
          "code": "kg"
        },
        "resourceType": "Observation"
      }
    },
    {
      "fullUrl": "urn:uuid:a0c115b9-8e9e-428f-befa-0abdb8aa2e4c",
      "resource": {
        "id": "a0c115b9-8e9e-428f-befa-0abdb8aa2e4c",
        "meta": {
          "profile": [
            "http://standardhealthrecord.org/fhir/StructureDefinition/shr-observation-Observation",
            "http://standardhealthrecord.org/fhir/StructureDefinition/shr-vital-VitalSign",
            "http://standardhealthrecord.org/fhir/StructureDefinition/shr-vital-BodyMassIndex"
          ]
        },
        "status": "final",
        "category": [
          {
            "coding": [
              {
                "system": "http://hl7.org/fhir/observation-category",
                "code": "vital-signs"
              }
            ]
          }
        ],
        "code": {
          "coding": [
            {
              "system": "http://loinc.org",
              "code": "39156-5",
              "display": "Body Mass Index"
            }
          ],
          "text": "Body Mass Index"
        },
        "subject": {
          "reference": "urn:uuid:c7f974eb-e315-44a1-8d70-61fad4c6c6bd"
        },
        "context": {
          "reference": "urn:uuid:203a007e-fc81-47bd-a552-d0f2e8aede45"
        },
        "effectiveDateTime": "2008-01-03T19:56:24-05:00",
        "issued": "2008-01-03T19:56:24-05:00",
        "valueQuantity": {
          "value": 41.17029473408459,
          "unit": "kg/m2",
          "system": "http://unitsofmeasure.org/",
          "code": "kg/m2"
        },
        "resourceType": "Observation"
      }
    },
    {
      "fullUrl": "urn:uuid:6391eb3a-2378-43a9-9b6d-71a1a3ac2b65",
      "resource": {
        "id": "6391eb3a-2378-43a9-9b6d-71a1a3ac2b65",
        "meta": {
          "profile": [
            "http://standardhealthrecord.org/fhir/StructureDefinition/shr-observation-Observation",
            "http://standardhealthrecord.org/fhir/StructureDefinition/shr-vital-BloodPressure"
          ]
        },
        "status": "final",
        "category": [
          {
            "coding": [
              {
                "system": "http://hl7.org/fhir/observation-category",
                "code": "vital-signs"
              }
            ]
          }
        ],
        "code": {
          "coding": [
            {
              "system": "http://loinc.org",
              "code": "55284-4",
              "display": "Blood Pressure"
            }
          ]
        },
        "subject": {
          "reference": "urn:uuid:c7f974eb-e315-44a1-8d70-61fad4c6c6bd"
        },
        "context": {
          "reference": "urn:uuid:203a007e-fc81-47bd-a552-d0f2e8aede45"
        },
        "effectiveDateTime": "2008-01-03T19:56:24-05:00",
        "issued": "2008-01-03T19:56:24-05:00",
        "component": [
          {
            "code": {
              "coding": [
                {
                  "system": "http://loinc.org",
                  "code": "8480-6",
                  "display": "Systolic Blood Pressure"
                }
              ],
              "text": "Systolic Blood Pressure"
            },
            "valueQuantity": {
              "value": 117,
              "unit": "mmHg",
              "system": "http://unitsofmeasure.org/",
              "code": "mmHg"
            }
          },
          {
            "code": {
              "coding": [
                {
                  "system": "http://loinc.org",
                  "code": "8462-4",
                  "display": "Diastolic Blood Pressure"
                }
              ],
              "text": "Diastolic Blood Pressure"
            },
            "valueQuantity": {
              "value": 83,
              "unit": "mmHg",
              "system": "http://unitsofmeasure.org/",
              "code": "mmHg"
            }
          }
        ],
        "resourceType": "Observation"
      }
    },
    {
      "fullUrl": "urn:uuid:5d01bcc5-71b2-4cdb-9244-3de58d238d6d",
      "resource": {
        "id": "5d01bcc5-71b2-4cdb-9244-3de58d238d6d",
        "meta": {
          "profile": [
            "http://standardhealthrecord.org/fhir/StructureDefinition/shr-observation-Observation"
          ]
        },
        "status": "final",
        "category": [
          {
            "coding": [
              {
                "system": "http://hl7.org/fhir/observation-category",
                "code": "procedure"
              }
            ]
          }
        ],
        "code": {
          "coding": [
            {
              "system": "http://loinc.org",
              "code": "19926-5",
              "display": "FEV1/​FVC"
            }
          ],
          "text": "FEV1/​FVC"
        },
        "subject": {
          "reference": "urn:uuid:c7f974eb-e315-44a1-8d70-61fad4c6c6bd"
        },
        "context": {
          "reference": "urn:uuid:203a007e-fc81-47bd-a552-d0f2e8aede45"
        },
        "effectiveDateTime": "2008-01-03T19:56:24-05:00",
        "issued": "2008-01-03T19:56:24-05:00",
        "valueQuantity": {
          "value": 48,
          "unit": "%",
          "system": "http://unitsofmeasure.org/",
          "code": "%"
        },
        "resourceType": "Observation"
      }
    },
    {
      "resource": {
        "meta": {
          "profile": [
            "http://standardhealthrecord.org/fhir/StructureDefinition/shr-procedure-Procedure"
          ]
        },
        "extension": [
          {
            "url": "http://standardhealthrecord.org/fhir/StructureDefinition/shr-core-CodeableConcept-extension",
            "valueCodeableConcept": {
              "coding": [
                {
                  "system": "http://snomed.info/sct",
                  "code": "127783003",
                  "display": "Spirometry (procedure)"
                }
              ],
              "text": "Spirometry (procedure)"
            }
          }
        ],
        "status": "completed",
        "code": {
          "coding": [
            {
              "system": "http://snomed.info/sct",
              "code": "127783003",
              "display": "Spirometry (procedure)"
            }
          ],
          "text": "Spirometry (procedure)"
        },
        "subject": {
          "reference": "urn:uuid:c7f974eb-e315-44a1-8d70-61fad4c6c6bd"
        },
        "context": {
          "reference": "urn:uuid:203a007e-fc81-47bd-a552-d0f2e8aede45"
        },
        "performedDateTime": "2008-01-03T19:56:24-05:00",
        "reasonReference": {
          "reference": "urn:uuid:2be7881c-89f2-4f8d-a9df-e2d53701c925",
          "display": "Pulmonary emphysema (disorder)"
        },
        "resourceType": "Procedure"
      }
    },
    {
      "resource": {
        "meta": {
          "profile": [
            "http://standardhealthrecord.org/fhir/StructureDefinition/shr-immunization-Immunization"
          ]
        },
        "status": "completed",
        "notGiven": false,
        "vaccineCode": {
          "coding": [
            {
              "system": "http://hl7.org/fhir/sid/cvx",
              "code": "140",
              "display": "Influenza, seasonal, injectable, preservative free"
            }
          ],
          "text": "Influenza, seasonal, injectable, preservative free"
        },
        "patient": {
          "reference": "urn:uuid:c7f974eb-e315-44a1-8d70-61fad4c6c6bd"
        },
        "encounter": {
          "reference": "urn:uuid:203a007e-fc81-47bd-a552-d0f2e8aede45"
        },
        "date": "2008-01-03T19:56:24-05:00",
        "primarySource": true,
        "resourceType": "Immunization"
      }
    },
    {
      "resource": {
        "status": "active",
        "category": [
          {
            "coding": [
              {
                "system": "http://snomed.info/sct",
                "code": "412776001",
                "display": "Chronic obstructive pulmonary disease clinical management plan"
              }
            ]
          }
        ],
        "subject": {
          "reference": "urn:uuid:c7f974eb-e315-44a1-8d70-61fad4c6c6bd"
        },
        "context": {
          "reference": "urn:uuid:203a007e-fc81-47bd-a552-d0f2e8aede45"
        },
        "period": {
          "start": "2006-12-17"
        },
        "addresses": [
          {
            "reference": "urn:uuid:2be7881c-89f2-4f8d-a9df-e2d53701c925"
          }
        ],
        "activity": [
          {
            "detail": {
              "code": {
                "coding": [
                  {
                    "system": "http://snomed.info/sct",
                    "code": "710081004",
                    "display": "Smoking cessation therapy"
                  }
                ]
              },
              "status": "in-progress"
            }
          },
          {
            "detail": {
              "code": {
                "coding": [
                  {
                    "system": "http://snomed.info/sct",
                    "code": "426990007",
                    "display": "Home oxygen therapy (procedure)"
                  }
                ]
              },
              "status": "in-progress"
            }
          }
        ],
        "resourceType": "CarePlan"
      }
    },
    {
      "fullUrl": "urn:uuid:f5b6022a-773d-4004-bed9-16cb14057ba4",
      "resource": {
        "id": "f5b6022a-773d-4004-bed9-16cb14057ba4",
        "meta": {
          "profile": [
            "http://standardhealthrecord.org/fhir/StructureDefinition/shr-medication-Medication"
          ]
        },
        "code": {
          "coding": [
            {
              "system": "http://www.nlm.nih.gov/research/umls/rxnorm",
              "code": "834060",
              "display": "Penicillin V Potassium 250 MG"
            }
          ],
          "text": "Penicillin V Potassium 250 MG"
        },
        "resourceType": "Medication"
      }
    },
    {
      "fullUrl": "urn:uuid:c7093dd4-4011-4842-b6f9-a7c64fa9f337",
      "resource": {
        "id": "c7093dd4-4011-4842-b6f9-a7c64fa9f337",
        "meta": {
          "profile": [
            "http://standardhealthrecord.org/fhir/StructureDefinition/shr-medication-MedicationPrescription"
          ]
        },
        "extension": [
          {
            "url": "http://standardhealthrecord.org/fhir/StructureDefinition/shr-base-ActionCode-extension",
            "valueCodeableConcept": {
              "coding": [
                {
                  "system": "http://snomed.info/sct",
                  "code": "33633005",
                  "display": "Prescription of drug (procedure)"
                }
              ],
              "text": "Prescription of drug (procedure)"
            }
          }
        ],
        "status": "active",
        "intent": "order",
        "medicationReference": {
          "reference": "urn:uuid:f5b6022a-773d-4004-bed9-16cb14057ba4"
        },
        "subject": {
          "reference": "urn:uuid:c7f974eb-e315-44a1-8d70-61fad4c6c6bd"
        },
        "context": {
          "reference": "urn:uuid:203a007e-fc81-47bd-a552-d0f2e8aede45"
        },
        "authoredOn": "1973-12-02",
        "resourceType": "MedicationRequest"
      }
    },
    {
      "fullUrl": "urn:uuid:df050f2b-2128-4b0b-8fcd-8cd637c12994",
      "resource": {
        "id": "df050f2b-2128-4b0b-8fcd-8cd637c12994",
        "meta": {
          "profile": [
            "http://standardhealthrecord.org/fhir/StructureDefinition/shr-medication-Medication"
          ]
        },
        "code": {
          "coding": [
            {
              "system": "http://www.nlm.nih.gov/research/umls/rxnorm",
              "code": "834101",
              "display": "Penicillin V Potassium 500 MG"
            }
          ],
          "text": "Penicillin V Potassium 500 MG"
        },
        "resourceType": "Medication"
      }
    },
    {
      "fullUrl": "urn:uuid:233e23cc-f165-4794-9c9b-11f821c001ee",
      "resource": {
        "id": "233e23cc-f165-4794-9c9b-11f821c001ee",
        "meta": {
          "profile": [
            "http://standardhealthrecord.org/fhir/StructureDefinition/shr-medication-MedicationPrescription"
          ]
        },
        "extension": [
          {
            "url": "http://standardhealthrecord.org/fhir/StructureDefinition/shr-base-ActionCode-extension",
            "valueCodeableConcept": {
              "coding": [
                {
                  "system": "http://snomed.info/sct",
                  "code": "33633005",
                  "display": "Prescription of drug (procedure)"
                }
              ],
              "text": "Prescription of drug (procedure)"
            }
          }
        ],
        "status": "active",
        "intent": "order",
        "medicationReference": {
          "reference": "urn:uuid:df050f2b-2128-4b0b-8fcd-8cd637c12994"
        },
        "subject": {
          "reference": "urn:uuid:c7f974eb-e315-44a1-8d70-61fad4c6c6bd"
        },
        "context": {
          "reference": "urn:uuid:203a007e-fc81-47bd-a552-d0f2e8aede45"
        },
        "authoredOn": "1994-03-16",
        "resourceType": "MedicationRequest"
      }
    },
    {
      "fullUrl": "urn:uuid:91808549-702f-4bd4-a9bf-1d90d64915c8",
      "resource": {
        "id": "91808549-702f-4bd4-a9bf-1d90d64915c8",
        "meta": {
          "profile": [
            "http://standardhealthrecord.org/fhir/StructureDefinition/shr-medication-Medication"
          ]
        },
        "code": {
          "coding": [
            {
              "system": "http://www.nlm.nih.gov/research/umls/rxnorm",
              "code": "896188",
              "display": "Fluticasone propionate 0.25 MG/ACTUAT / salmeterol 0.05 MG/ACTUAT [Advair]"
            }
          ],
          "text": "Fluticasone propionate 0.25 MG/ACTUAT / salmeterol 0.05 MG/ACTUAT [Advair]"
        },
        "resourceType": "Medication"
      }
    },
    {
      "fullUrl": "urn:uuid:5de1be00-5299-47b0-8174-d0589bb13bf5",
      "resource": {
        "id": "5de1be00-5299-47b0-8174-d0589bb13bf5",
        "meta": {
          "profile": [
            "http://standardhealthrecord.org/fhir/StructureDefinition/shr-medication-MedicationPrescription"
          ]
        },
        "extension": [
          {
            "url": "http://standardhealthrecord.org/fhir/StructureDefinition/shr-base-ActionCode-extension",
            "valueCodeableConcept": {
              "coding": [
                {
                  "system": "http://snomed.info/sct",
                  "code": "33633005",
                  "display": "Prescription of drug (procedure)"
                }
              ],
              "text": "Prescription of drug (procedure)"
            }
          }
        ],
        "status": "active",
        "intent": "order",
        "medicationReference": {
          "reference": "urn:uuid:91808549-702f-4bd4-a9bf-1d90d64915c8"
        },
        "subject": {
          "reference": "urn:uuid:c7f974eb-e315-44a1-8d70-61fad4c6c6bd"
        },
        "context": {
          "reference": "urn:uuid:203a007e-fc81-47bd-a552-d0f2e8aede45"
        },
        "authoredOn": "2008-01-03",
        "reasonReference": [
          {
            "reference": "urn:uuid:2be7881c-89f2-4f8d-a9df-e2d53701c925"
          }
        ],
        "resourceType": "MedicationRequest"
      }
    },
    {
      "fullUrl": "urn:uuid:9c3f5c64-d3fc-4205-97a9-705049d69f11",
      "resource": {
        "id": "9c3f5c64-d3fc-4205-97a9-705049d69f11",
        "meta": {
          "profile": [
            "http://standardhealthrecord.org/fhir/StructureDefinition/shr-encounter-Encounter"
          ]
        },
        "status": "finished",
        "class": {
          "code": "ambulatory"
        },
        "type": [
          {
            "coding": [
              {
                "system": "http://snomed.info/sct",
                "code": "185345009"
              }
            ],
            "text": "Encounter for symptom"
          }
        ],
        "subject": {
          "reference": "urn:uuid:c7f974eb-e315-44a1-8d70-61fad4c6c6bd"
        },
        "period": {
          "start": "2008-09-14T15:00:55-04:00",
          "end": "2008-09-14T15:16:58-04:00"
        },
        "reason": {
          "coding": [
            {
              "system": "http://snomed.info/sct",
              "code": "10509002",
              "display": "Acute bronchitis (disorder)"
            }
          ]
        },
        "serviceProvider": {
          "reference": "urn:uuid:432ec178-094d-436f-8652-b99faac06775"
        },
        "resourceType": "Encounter"
      }
    },
    {
      "fullUrl": "urn:uuid:75942f7b-b2ba-4da1-ae2d-b5166adf9b42",
      "resource": {
        "id": "75942f7b-b2ba-4da1-ae2d-b5166adf9b42",
        "meta": {
          "profile": [
            "http://standardhealthrecord.org/fhir/StructureDefinition/shr-problem-Problem"
          ]
        },
        "clinicalStatus": "active",
        "verificationStatus": "confirmed",
        "code": {
          "coding": [
            {
              "system": "http://snomed.info/sct",
              "code": "10509002",
              "display": "Acute bronchitis (disorder)"
            }
          ],
          "text": "Acute bronchitis (disorder)"
        },
        "subject": {
          "reference": "urn:uuid:c7f974eb-e315-44a1-8d70-61fad4c6c6bd"
        },
        "context": {
          "reference": "urn:uuid:9c3f5c64-d3fc-4205-97a9-705049d69f11"
        },
        "onsetDateTime": "2008-09-13T09:43:56-04:00",
        "abatementDateTime": "2008-09-23T12:45:16-04:00",
        "assertedDate": "2008-09-13",
        "resourceType": "Condition"
      }
    },
    {
      "resource": {
        "meta": {
          "profile": [
            "http://standardhealthrecord.org/fhir/StructureDefinition/shr-procedure-Procedure"
          ]
        },
        "extension": [
          {
            "url": "http://standardhealthrecord.org/fhir/StructureDefinition/shr-core-CodeableConcept-extension",
            "valueCodeableConcept": {
              "coding": [
                {
                  "system": "http://snomed.info/sct",
                  "code": "23426006",
                  "display": "Measurement of respiratory function (procedure)"
                }
              ],
              "text": "Measurement of respiratory function (procedure)"
            }
          }
        ],
        "status": "completed",
        "code": {
          "coding": [
            {
              "system": "http://snomed.info/sct",
              "code": "23426006",
              "display": "Measurement of respiratory function (procedure)"
            }
          ],
          "text": "Measurement of respiratory function (procedure)"
        },
        "subject": {
          "reference": "urn:uuid:c7f974eb-e315-44a1-8d70-61fad4c6c6bd"
        },
        "context": {
          "reference": "urn:uuid:9c3f5c64-d3fc-4205-97a9-705049d69f11"
        },
        "performedPeriod": {
          "start": "2008-09-14T15:00:55-04:00",
          "end": "2008-09-14T15:24:12-04:00"
        },
        "reasonReference": {
          "reference": "urn:uuid:75942f7b-b2ba-4da1-ae2d-b5166adf9b42",
          "display": "Acute bronchitis (disorder)"
        },
        "resourceType": "Procedure"
      }
    },
    {
      "resource": {
        "status": "completed",
        "category": [
          {
            "coding": [
              {
                "system": "http://snomed.info/sct",
                "code": "53950000",
                "display": "Respiratory therapy"
              }
            ]
          }
        ],
        "subject": {
          "reference": "urn:uuid:c7f974eb-e315-44a1-8d70-61fad4c6c6bd"
        },
        "context": {
          "reference": "urn:uuid:9c3f5c64-d3fc-4205-97a9-705049d69f11"
        },
        "period": {
          "start": "2008-09-14",
          "end": "2009-10-04"
        },
        "addresses": [
          {
            "reference": "urn:uuid:75942f7b-b2ba-4da1-ae2d-b5166adf9b42"
          }
        ],
        "activity": [
          {
            "detail": {
              "code": {
                "coding": [
                  {
                    "system": "http://snomed.info/sct",
                    "code": "710081004",
                    "display": "Smoking cessation therapy"
                  }
                ]
              },
              "status": "completed"
            }
          },
          {
            "detail": {
              "code": {
                "coding": [
                  {
                    "system": "http://snomed.info/sct",
                    "code": "304510005",
                    "display": "Recommendation to avoid exercise"
                  }
                ]
              },
              "status": "completed"
            }
          },
          {
            "detail": {
              "code": {
                "coding": [
                  {
                    "system": "http://snomed.info/sct",
                    "code": "371605008",
                    "display": "Deep breathing and coughing exercises"
                  }
                ]
              },
              "status": "completed"
            }
          }
        ],
        "resourceType": "CarePlan"
      }
    },
    {
      "fullUrl": "urn:uuid:e5355133-4807-4846-8578-352811fe081b",
      "resource": {
        "id": "e5355133-4807-4846-8578-352811fe081b",
        "meta": {
          "profile": [
            "http://standardhealthrecord.org/fhir/StructureDefinition/shr-medication-Medication"
          ]
        },
        "code": {
          "coding": [
            {
              "system": "http://www.nlm.nih.gov/research/umls/rxnorm",
              "code": "608680",
              "display": "Acetaminophen 160 MG"
            }
          ],
          "text": "Acetaminophen 160 MG"
        },
        "resourceType": "Medication"
      }
    },
    {
      "fullUrl": "urn:uuid:e77299d8-33c5-47d6-880f-be8d52c9201b",
      "resource": {
        "id": "e77299d8-33c5-47d6-880f-be8d52c9201b",
        "meta": {
          "profile": [
            "http://standardhealthrecord.org/fhir/StructureDefinition/shr-medication-MedicationPrescription"
          ]
        },
        "extension": [
          {
            "url": "http://standardhealthrecord.org/fhir/StructureDefinition/shr-base-ActionCode-extension",
            "valueCodeableConcept": {
              "coding": [
                {
                  "system": "http://snomed.info/sct",
                  "code": "33633005",
                  "display": "Prescription of drug (procedure)"
                }
              ],
              "text": "Prescription of drug (procedure)"
            }
          }
        ],
        "status": "stopped",
        "intent": "order",
        "medicationReference": {
          "reference": "urn:uuid:e5355133-4807-4846-8578-352811fe081b"
        },
        "subject": {
          "reference": "urn:uuid:c7f974eb-e315-44a1-8d70-61fad4c6c6bd"
        },
        "context": {
          "reference": "urn:uuid:9c3f5c64-d3fc-4205-97a9-705049d69f11"
        },
        "authoredOn": "2008-09-14",
        "reasonReference": [
          {
            "reference": "urn:uuid:75942f7b-b2ba-4da1-ae2d-b5166adf9b42"
          }
        ],
        "resourceType": "MedicationRequest"
      }
    },
    {
      "fullUrl": "urn:uuid:b0b72dc8-48ee-44af-9b63-fe5a5b9ff8d3",
      "resource": {
        "id": "b0b72dc8-48ee-44af-9b63-fe5a5b9ff8d3",
        "meta": {
          "profile": [
            "http://standardhealthrecord.org/fhir/StructureDefinition/shr-encounter-Encounter"
          ]
        },
        "status": "finished",
        "class": {
          "code": "outpatient"
        },
        "type": [
          {
            "coding": [
              {
                "system": "http://snomed.info/sct",
                "code": "185349003"
              }
            ],
            "text": "Outpatient Encounter"
          }
        ],
        "subject": {
          "reference": "urn:uuid:c7f974eb-e315-44a1-8d70-61fad4c6c6bd"
        },
        "period": {
          "start": "2009-10-04T16:13:21-04:00",
          "end": "2009-10-04T17:13:21-04:00"
        },
        "serviceProvider": {
          "reference": "urn:uuid:432ec178-094d-436f-8652-b99faac06775"
        },
        "resourceType": "Encounter"
      }
    },
    {
      "fullUrl": "urn:uuid:4de72a45-301b-4cb4-9a8b-faed40be729a",
      "resource": {
        "id": "4de72a45-301b-4cb4-9a8b-faed40be729a",
        "meta": {
          "profile": [
            "http://standardhealthrecord.org/fhir/StructureDefinition/shr-observation-Observation",
            "http://standardhealthrecord.org/fhir/StructureDefinition/shr-vital-VitalSign",
            "http://standardhealthrecord.org/fhir/StructureDefinition/shr-vital-BodyHeight"
          ]
        },
        "status": "final",
        "category": [
          {
            "coding": [
              {
                "system": "http://hl7.org/fhir/observation-category",
                "code": "vital-signs"
              }
            ]
          }
        ],
        "code": {
          "coding": [
            {
              "system": "http://loinc.org",
              "code": "8302-2",
              "display": "Body Height"
            }
          ],
          "text": "Body Height"
        },
        "subject": {
          "reference": "urn:uuid:c7f974eb-e315-44a1-8d70-61fad4c6c6bd"
        },
        "context": {
          "reference": "urn:uuid:b0b72dc8-48ee-44af-9b63-fe5a5b9ff8d3"
        },
        "effectiveDateTime": "2009-10-04T16:13:21-04:00",
        "issued": "2009-10-04T16:13:21-04:00",
        "valueQuantity": {
          "value": 172.77271219700336,
          "unit": "cm",
          "system": "http://unitsofmeasure.org/",
          "code": "cm"
        },
        "resourceType": "Observation"
      }
    },
    {
      "fullUrl": "urn:uuid:7b337344-e840-4bd7-8102-44a91af871f2",
      "resource": {
        "id": "7b337344-e840-4bd7-8102-44a91af871f2",
        "meta": {
          "profile": [
            "http://standardhealthrecord.org/fhir/StructureDefinition/shr-observation-Observation",
            "http://standardhealthrecord.org/fhir/StructureDefinition/shr-vital-VitalSign",
            "http://standardhealthrecord.org/fhir/StructureDefinition/shr-vital-BodyWeight"
          ]
        },
        "status": "final",
        "category": [
          {
            "coding": [
              {
                "system": "http://hl7.org/fhir/observation-category",
                "code": "vital-signs"
              }
            ]
          }
        ],
        "code": {
          "coding": [
            {
              "system": "http://loinc.org",
              "code": "29463-7",
              "display": "Body Weight"
            }
          ],
          "text": "Body Weight"
        },
        "subject": {
          "reference": "urn:uuid:c7f974eb-e315-44a1-8d70-61fad4c6c6bd"
        },
        "context": {
          "reference": "urn:uuid:b0b72dc8-48ee-44af-9b63-fe5a5b9ff8d3"
        },
        "effectiveDateTime": "2009-10-04T16:13:21-04:00",
        "issued": "2009-10-04T16:13:21-04:00",
        "valueQuantity": {
          "value": 126.12752952379222,
          "unit": "kg",
          "system": "http://unitsofmeasure.org/",
          "code": "kg"
        },
        "resourceType": "Observation"
      }
    },
    {
      "fullUrl": "urn:uuid:3c1cf4c5-8741-4ad3-b2a4-3b034d13978e",
      "resource": {
        "id": "3c1cf4c5-8741-4ad3-b2a4-3b034d13978e",
        "meta": {
          "profile": [
            "http://standardhealthrecord.org/fhir/StructureDefinition/shr-observation-Observation",
            "http://standardhealthrecord.org/fhir/StructureDefinition/shr-vital-VitalSign",
            "http://standardhealthrecord.org/fhir/StructureDefinition/shr-vital-BodyMassIndex"
          ]
        },
        "status": "final",
        "category": [
          {
            "coding": [
              {
                "system": "http://hl7.org/fhir/observation-category",
                "code": "vital-signs"
              }
            ]
          }
        ],
        "code": {
          "coding": [
            {
              "system": "http://loinc.org",
              "code": "39156-5",
              "display": "Body Mass Index"
            }
          ],
          "text": "Body Mass Index"
        },
        "subject": {
          "reference": "urn:uuid:c7f974eb-e315-44a1-8d70-61fad4c6c6bd"
        },
        "context": {
          "reference": "urn:uuid:b0b72dc8-48ee-44af-9b63-fe5a5b9ff8d3"
        },
        "effectiveDateTime": "2009-10-04T16:13:21-04:00",
        "issued": "2009-10-04T16:13:21-04:00",
        "valueQuantity": {
          "value": 42.25319825963966,
          "unit": "kg/m2",
          "system": "http://unitsofmeasure.org/",
          "code": "kg/m2"
        },
        "resourceType": "Observation"
      }
    },
    {
      "fullUrl": "urn:uuid:54d3244d-e7c7-40de-92c9-e5c7fd88d307",
      "resource": {
        "id": "54d3244d-e7c7-40de-92c9-e5c7fd88d307",
        "meta": {
          "profile": [
            "http://standardhealthrecord.org/fhir/StructureDefinition/shr-observation-Observation",
            "http://standardhealthrecord.org/fhir/StructureDefinition/shr-vital-BloodPressure"
          ]
        },
        "status": "final",
        "category": [
          {
            "coding": [
              {
                "system": "http://hl7.org/fhir/observation-category",
                "code": "vital-signs"
              }
            ]
          }
        ],
        "code": {
          "coding": [
            {
              "system": "http://loinc.org",
              "code": "55284-4",
              "display": "Blood Pressure"
            }
          ]
        },
        "subject": {
          "reference": "urn:uuid:c7f974eb-e315-44a1-8d70-61fad4c6c6bd"
        },
        "context": {
          "reference": "urn:uuid:b0b72dc8-48ee-44af-9b63-fe5a5b9ff8d3"
        },
        "effectiveDateTime": "2009-10-04T16:13:21-04:00",
        "issued": "2009-10-04T16:13:21-04:00",
        "component": [
          {
            "code": {
              "coding": [
                {
                  "system": "http://loinc.org",
                  "code": "8480-6",
                  "display": "Systolic Blood Pressure"
                }
              ],
              "text": "Systolic Blood Pressure"
            },
            "valueQuantity": {
              "value": 110,
              "unit": "mmHg",
              "system": "http://unitsofmeasure.org/",
              "code": "mmHg"
            }
          },
          {
            "code": {
              "coding": [
                {
                  "system": "http://loinc.org",
                  "code": "8462-4",
                  "display": "Diastolic Blood Pressure"
                }
              ],
              "text": "Diastolic Blood Pressure"
            },
            "valueQuantity": {
              "value": 86,
              "unit": "mmHg",
              "system": "http://unitsofmeasure.org/",
              "code": "mmHg"
            }
          }
        ],
        "resourceType": "Observation"
      }
    },
    {
      "fullUrl": "urn:uuid:2cffecbc-e5c1-4d11-a2fe-d3b9caed8026",
      "resource": {
        "id": "2cffecbc-e5c1-4d11-a2fe-d3b9caed8026",
        "meta": {
          "profile": [
            "http://standardhealthrecord.org/fhir/StructureDefinition/shr-observation-Observation"
          ]
        },
        "status": "final",
        "category": [
          {
            "coding": [
              {
                "system": "http://hl7.org/fhir/observation-category",
                "code": "procedure"
              }
            ]
          }
        ],
        "code": {
          "coding": [
            {
              "system": "http://loinc.org",
              "code": "19926-5",
              "display": "FEV1/​FVC"
            }
          ],
          "text": "FEV1/​FVC"
        },
        "subject": {
          "reference": "urn:uuid:c7f974eb-e315-44a1-8d70-61fad4c6c6bd"
        },
        "context": {
          "reference": "urn:uuid:b0b72dc8-48ee-44af-9b63-fe5a5b9ff8d3"
        },
        "effectiveDateTime": "2009-10-04T16:13:21-04:00",
        "issued": "2009-10-04T16:13:21-04:00",
        "valueQuantity": {
          "value": 33,
          "unit": "%",
          "system": "http://unitsofmeasure.org/",
          "code": "%"
        },
        "resourceType": "Observation"
      }
    },
    {
      "resource": {
        "meta": {
          "profile": [
            "http://standardhealthrecord.org/fhir/StructureDefinition/shr-procedure-Procedure"
          ]
        },
        "extension": [
          {
            "url": "http://standardhealthrecord.org/fhir/StructureDefinition/shr-core-CodeableConcept-extension",
            "valueCodeableConcept": {
              "coding": [
                {
                  "system": "http://snomed.info/sct",
                  "code": "428191000124101",
                  "display": "Documentation of current medications"
                }
              ],
              "text": "Documentation of current medications"
            }
          }
        ],
        "status": "completed",
        "code": {
          "coding": [
            {
              "system": "http://snomed.info/sct",
              "code": "428191000124101",
              "display": "Documentation of current medications"
            }
          ],
          "text": "Documentation of current medications"
        },
        "subject": {
          "reference": "urn:uuid:c7f974eb-e315-44a1-8d70-61fad4c6c6bd"
        },
        "context": {
          "reference": "urn:uuid:b0b72dc8-48ee-44af-9b63-fe5a5b9ff8d3"
        },
        "performedDateTime": "2009-10-04T16:13:21-04:00",
        "resourceType": "Procedure"
      }
    },
    {
      "resource": {
        "meta": {
          "profile": [
            "http://standardhealthrecord.org/fhir/StructureDefinition/shr-procedure-Procedure"
          ]
        },
        "extension": [
          {
            "url": "http://standardhealthrecord.org/fhir/StructureDefinition/shr-core-CodeableConcept-extension",
            "valueCodeableConcept": {
              "coding": [
                {
                  "system": "http://snomed.info/sct",
                  "code": "127783003",
                  "display": "Spirometry (procedure)"
                }
              ],
              "text": "Spirometry (procedure)"
            }
          }
        ],
        "status": "completed",
        "code": {
          "coding": [
            {
              "system": "http://snomed.info/sct",
              "code": "127783003",
              "display": "Spirometry (procedure)"
            }
          ],
          "text": "Spirometry (procedure)"
        },
        "subject": {
          "reference": "urn:uuid:c7f974eb-e315-44a1-8d70-61fad4c6c6bd"
        },
        "context": {
          "reference": "urn:uuid:b0b72dc8-48ee-44af-9b63-fe5a5b9ff8d3"
        },
        "performedDateTime": "2009-10-04T16:13:21-04:00",
        "reasonReference": {
          "reference": "urn:uuid:2be7881c-89f2-4f8d-a9df-e2d53701c925",
          "display": "Pulmonary emphysema (disorder)"
        },
        "resourceType": "Procedure"
      }
    },
    {
      "resource": {
        "meta": {
          "profile": [
            "http://standardhealthrecord.org/fhir/StructureDefinition/shr-immunization-Immunization"
          ]
        },
        "status": "completed",
        "notGiven": false,
        "vaccineCode": {
          "coding": [
            {
              "system": "http://hl7.org/fhir/sid/cvx",
              "code": "140",
              "display": "Influenza, seasonal, injectable, preservative free"
            }
          ],
          "text": "Influenza, seasonal, injectable, preservative free"
        },
        "patient": {
          "reference": "urn:uuid:c7f974eb-e315-44a1-8d70-61fad4c6c6bd"
        },
        "encounter": {
          "reference": "urn:uuid:b0b72dc8-48ee-44af-9b63-fe5a5b9ff8d3"
        },
        "date": "2009-10-04T16:13:21-04:00",
        "primarySource": true,
        "resourceType": "Immunization"
      }
    },
    {
      "fullUrl": "urn:uuid:b2e22698-ed6d-49b6-9983-80077f2481a8",
      "resource": {
        "id": "b2e22698-ed6d-49b6-9983-80077f2481a8",
        "meta": {
          "profile": [
            "http://standardhealthrecord.org/fhir/StructureDefinition/shr-encounter-Encounter"
          ]
        },
        "status": "finished",
        "class": {
          "code": "outpatient"
        },
        "type": [
          {
            "coding": [
              {
                "system": "http://snomed.info/sct",
                "code": "185349003"
              }
            ],
            "text": "Outpatient Encounter"
          }
        ],
        "subject": {
          "reference": "urn:uuid:c7f974eb-e315-44a1-8d70-61fad4c6c6bd"
        },
        "period": {
          "start": "2012-08-23T08:31:33-04:00",
          "end": "2012-08-23T09:31:33-04:00"
        },
        "serviceProvider": {
          "reference": "urn:uuid:432ec178-094d-436f-8652-b99faac06775"
        },
        "resourceType": "Encounter"
      }
    },
    {
      "fullUrl": "urn:uuid:c12618c0-4d60-4ccd-9b42-8858202358b5",
      "resource": {
        "id": "c12618c0-4d60-4ccd-9b42-8858202358b5",
        "meta": {
          "profile": [
            "http://standardhealthrecord.org/fhir/StructureDefinition/shr-observation-Observation",
            "http://standardhealthrecord.org/fhir/StructureDefinition/shr-vital-VitalSign",
            "http://standardhealthrecord.org/fhir/StructureDefinition/shr-vital-BodyHeight"
          ]
        },
        "status": "final",
        "category": [
          {
            "coding": [
              {
                "system": "http://hl7.org/fhir/observation-category",
                "code": "vital-signs"
              }
            ]
          }
        ],
        "code": {
          "coding": [
            {
              "system": "http://loinc.org",
              "code": "8302-2",
              "display": "Body Height"
            }
          ],
          "text": "Body Height"
        },
        "subject": {
          "reference": "urn:uuid:c7f974eb-e315-44a1-8d70-61fad4c6c6bd"
        },
        "context": {
          "reference": "urn:uuid:b2e22698-ed6d-49b6-9983-80077f2481a8"
        },
        "effectiveDateTime": "2012-08-23T08:31:33-04:00",
        "issued": "2012-08-23T08:31:33-04:00",
        "valueQuantity": {
          "value": 172.77271219700336,
          "unit": "cm",
          "system": "http://unitsofmeasure.org/",
          "code": "cm"
        },
        "resourceType": "Observation"
      }
    },
    {
      "fullUrl": "urn:uuid:9ecf7ce2-a31d-4388-b2a8-e14587775096",
      "resource": {
        "id": "9ecf7ce2-a31d-4388-b2a8-e14587775096",
        "meta": {
          "profile": [
            "http://standardhealthrecord.org/fhir/StructureDefinition/shr-observation-Observation",
            "http://standardhealthrecord.org/fhir/StructureDefinition/shr-vital-VitalSign",
            "http://standardhealthrecord.org/fhir/StructureDefinition/shr-vital-BodyWeight"
          ]
        },
        "status": "final",
        "category": [
          {
            "coding": [
              {
                "system": "http://hl7.org/fhir/observation-category",
                "code": "vital-signs"
              }
            ]
          }
        ],
        "code": {
          "coding": [
            {
              "system": "http://loinc.org",
              "code": "29463-7",
              "display": "Body Weight"
            }
          ],
          "text": "Body Weight"
        },
        "subject": {
          "reference": "urn:uuid:c7f974eb-e315-44a1-8d70-61fad4c6c6bd"
        },
        "context": {
          "reference": "urn:uuid:b2e22698-ed6d-49b6-9983-80077f2481a8"
        },
        "effectiveDateTime": "2012-08-23T08:31:33-04:00",
        "issued": "2012-08-23T08:31:33-04:00",
        "valueQuantity": {
          "value": 131.01315520168563,
          "unit": "kg",
          "system": "http://unitsofmeasure.org/",
          "code": "kg"
        },
        "resourceType": "Observation"
      }
    },
    {
      "fullUrl": "urn:uuid:c9a1d7fd-669f-4885-9c0e-d2904af0b01d",
      "resource": {
        "id": "c9a1d7fd-669f-4885-9c0e-d2904af0b01d",
        "meta": {
          "profile": [
            "http://standardhealthrecord.org/fhir/StructureDefinition/shr-observation-Observation",
            "http://standardhealthrecord.org/fhir/StructureDefinition/shr-vital-VitalSign",
            "http://standardhealthrecord.org/fhir/StructureDefinition/shr-vital-BodyMassIndex"
          ]
        },
        "status": "final",
        "category": [
          {
            "coding": [
              {
                "system": "http://hl7.org/fhir/observation-category",
                "code": "vital-signs"
              }
            ]
          }
        ],
        "code": {
          "coding": [
            {
              "system": "http://loinc.org",
              "code": "39156-5",
              "display": "Body Mass Index"
            }
          ],
          "text": "Body Mass Index"
        },
        "subject": {
          "reference": "urn:uuid:c7f974eb-e315-44a1-8d70-61fad4c6c6bd"
        },
        "context": {
          "reference": "urn:uuid:b2e22698-ed6d-49b6-9983-80077f2481a8"
        },
        "effectiveDateTime": "2012-08-23T08:31:33-04:00",
        "issued": "2012-08-23T08:31:33-04:00",
        "valueQuantity": {
          "value": 43.88990129481229,
          "unit": "kg/m2",
          "system": "http://unitsofmeasure.org/",
          "code": "kg/m2"
        },
        "resourceType": "Observation"
      }
    },
    {
      "fullUrl": "urn:uuid:0240f2a3-62c4-43fd-839c-66fd63dcefc8",
      "resource": {
        "id": "0240f2a3-62c4-43fd-839c-66fd63dcefc8",
        "meta": {
          "profile": [
            "http://standardhealthrecord.org/fhir/StructureDefinition/shr-observation-Observation",
            "http://standardhealthrecord.org/fhir/StructureDefinition/shr-vital-BloodPressure"
          ]
        },
        "status": "final",
        "category": [
          {
            "coding": [
              {
                "system": "http://hl7.org/fhir/observation-category",
                "code": "vital-signs"
              }
            ]
          }
        ],
        "code": {
          "coding": [
            {
              "system": "http://loinc.org",
              "code": "55284-4",
              "display": "Blood Pressure"
            }
          ]
        },
        "subject": {
          "reference": "urn:uuid:c7f974eb-e315-44a1-8d70-61fad4c6c6bd"
        },
        "context": {
          "reference": "urn:uuid:b2e22698-ed6d-49b6-9983-80077f2481a8"
        },
        "effectiveDateTime": "2012-08-23T08:31:33-04:00",
        "issued": "2012-08-23T08:31:33-04:00",
        "component": [
          {
            "code": {
              "coding": [
                {
                  "system": "http://loinc.org",
                  "code": "8480-6",
                  "display": "Systolic Blood Pressure"
                }
              ],
              "text": "Systolic Blood Pressure"
            },
            "valueQuantity": {
              "value": 135,
              "unit": "mmHg",
              "system": "http://unitsofmeasure.org/",
              "code": "mmHg"
            }
          },
          {
            "code": {
              "coding": [
                {
                  "system": "http://loinc.org",
                  "code": "8462-4",
                  "display": "Diastolic Blood Pressure"
                }
              ],
              "text": "Diastolic Blood Pressure"
            },
            "valueQuantity": {
              "value": 73,
              "unit": "mmHg",
              "system": "http://unitsofmeasure.org/",
              "code": "mmHg"
            }
          }
        ],
        "resourceType": "Observation"
      }
    },
    {
      "fullUrl": "urn:uuid:193b99f4-ddd9-43b3-8db7-4b16b2adabdc",
      "resource": {
        "id": "193b99f4-ddd9-43b3-8db7-4b16b2adabdc",
        "meta": {
          "profile": [
            "http://standardhealthrecord.org/fhir/StructureDefinition/shr-observation-Observation"
          ]
        },
        "status": "final",
        "category": [
          {
            "coding": [
              {
                "system": "http://hl7.org/fhir/observation-category",
                "code": "laboratory"
              }
            ]
          }
        ],
        "code": {
          "coding": [
            {
              "system": "http://loinc.org",
              "code": "2093-3",
              "display": "Total Cholesterol"
            }
          ],
          "text": "Total Cholesterol"
        },
        "subject": {
          "reference": "urn:uuid:c7f974eb-e315-44a1-8d70-61fad4c6c6bd"
        },
        "context": {
          "reference": "urn:uuid:b2e22698-ed6d-49b6-9983-80077f2481a8"
        },
        "effectiveDateTime": "2012-08-23T08:31:33-04:00",
        "issued": "2012-08-23T08:31:33-04:00",
        "valueQuantity": {
          "value": 184,
          "unit": "mg/dL",
          "system": "http://unitsofmeasure.org/",
          "code": "mg/dL"
        },
        "resourceType": "Observation"
      }
    },
    {
      "fullUrl": "urn:uuid:021f22b8-fa9b-405d-bf37-825d69414ad8",
      "resource": {
        "id": "021f22b8-fa9b-405d-bf37-825d69414ad8",
        "meta": {
          "profile": [
            "http://standardhealthrecord.org/fhir/StructureDefinition/shr-observation-Observation"
          ]
        },
        "status": "final",
        "category": [
          {
            "coding": [
              {
                "system": "http://hl7.org/fhir/observation-category",
                "code": "laboratory"
              }
            ]
          }
        ],
        "code": {
          "coding": [
            {
              "system": "http://loinc.org",
              "code": "2571-8",
              "display": "Triglycerides"
            }
          ],
          "text": "Triglycerides"
        },
        "subject": {
          "reference": "urn:uuid:c7f974eb-e315-44a1-8d70-61fad4c6c6bd"
        },
        "context": {
          "reference": "urn:uuid:b2e22698-ed6d-49b6-9983-80077f2481a8"
        },
        "effectiveDateTime": "2012-08-23T08:31:33-04:00",
        "issued": "2012-08-23T08:31:33-04:00",
        "valueQuantity": {
          "value": 102,
          "unit": "mg/dL",
          "system": "http://unitsofmeasure.org/",
          "code": "mg/dL"
        },
        "resourceType": "Observation"
      }
    },
    {
      "fullUrl": "urn:uuid:6a2f015e-9f65-40d5-802c-0bbde19fb441",
      "resource": {
        "id": "6a2f015e-9f65-40d5-802c-0bbde19fb441",
        "meta": {
          "profile": [
            "http://standardhealthrecord.org/fhir/StructureDefinition/shr-observation-Observation"
          ]
        },
        "status": "final",
        "category": [
          {
            "coding": [
              {
                "system": "http://hl7.org/fhir/observation-category",
                "code": "laboratory"
              }
            ]
          }
        ],
        "code": {
          "coding": [
            {
              "system": "http://loinc.org",
              "code": "18262-6",
              "display": "Low Density Lipoprotein Cholesterol"
            }
          ],
          "text": "Low Density Lipoprotein Cholesterol"
        },
        "subject": {
          "reference": "urn:uuid:c7f974eb-e315-44a1-8d70-61fad4c6c6bd"
        },
        "context": {
          "reference": "urn:uuid:b2e22698-ed6d-49b6-9983-80077f2481a8"
        },
        "effectiveDateTime": "2012-08-23T08:31:33-04:00",
        "issued": "2012-08-23T08:31:33-04:00",
        "valueQuantity": {
          "value": 95,
          "unit": "mg/dL",
          "system": "http://unitsofmeasure.org/",
          "code": "mg/dL"
        },
        "resourceType": "Observation"
      }
    },
    {
      "fullUrl": "urn:uuid:ec8134bf-739d-4030-88e2-978c89906cd3",
      "resource": {
        "id": "ec8134bf-739d-4030-88e2-978c89906cd3",
        "meta": {
          "profile": [
            "http://standardhealthrecord.org/fhir/StructureDefinition/shr-observation-Observation"
          ]
        },
        "status": "final",
        "category": [
          {
            "coding": [
              {
                "system": "http://hl7.org/fhir/observation-category",
                "code": "laboratory"
              }
            ]
          }
        ],
        "code": {
          "coding": [
            {
              "system": "http://loinc.org",
              "code": "2085-9",
              "display": "High Density Lipoprotein Cholesterol"
            }
          ],
          "text": "High Density Lipoprotein Cholesterol"
        },
        "subject": {
          "reference": "urn:uuid:c7f974eb-e315-44a1-8d70-61fad4c6c6bd"
        },
        "context": {
          "reference": "urn:uuid:b2e22698-ed6d-49b6-9983-80077f2481a8"
        },
        "effectiveDateTime": "2012-08-23T08:31:33-04:00",
        "issued": "2012-08-23T08:31:33-04:00",
        "valueQuantity": {
          "value": 68,
          "unit": "mg/dL",
          "system": "http://unitsofmeasure.org/",
          "code": "mg/dL"
        },
        "resourceType": "Observation"
      }
    },
    {
      "fullUrl": "urn:uuid:cf02a782-6355-4381-8ff5-67755145e996",
      "resource": {
        "id": "cf02a782-6355-4381-8ff5-67755145e996",
        "meta": {
          "profile": [
            "http://standardhealthrecord.org/fhir/StructureDefinition/shr-observation-Panel"
          ]
        },
        "status": "final",
        "code": {
          "coding": [
            {
              "system": "http://loinc.org",
              "code": "57698-3",
              "display": "Lipid Panel"
            }
          ]
        },
        "subject": {
          "reference": "urn:uuid:c7f974eb-e315-44a1-8d70-61fad4c6c6bd"
        },
        "context": {
          "reference": "urn:uuid:b2e22698-ed6d-49b6-9983-80077f2481a8"
        },
        "effectiveDateTime": "2012-08-23T08:31:33-04:00",
        "issued": "2012-08-23T08:31:33-04:00",
        "result": [
          {
            "reference": "urn:uuid:193b99f4-ddd9-43b3-8db7-4b16b2adabdc",
            "display": "Total Cholesterol"
          },
          {
            "reference": "urn:uuid:021f22b8-fa9b-405d-bf37-825d69414ad8",
            "display": "Triglycerides"
          },
          {
            "reference": "urn:uuid:6a2f015e-9f65-40d5-802c-0bbde19fb441",
            "display": "Low Density Lipoprotein Cholesterol"
          },
          {
            "reference": "urn:uuid:ec8134bf-739d-4030-88e2-978c89906cd3",
            "display": "High Density Lipoprotein Cholesterol"
          }
        ],
        "resourceType": "DiagnosticReport"
      }
    },
    {
      "fullUrl": "urn:uuid:2d5d4a05-8359-462e-9456-99db5a5b8b45",
      "resource": {
        "id": "2d5d4a05-8359-462e-9456-99db5a5b8b45",
        "meta": {
          "profile": [
            "http://standardhealthrecord.org/fhir/StructureDefinition/shr-observation-Observation"
          ]
        },
        "status": "final",
        "category": [
          {
            "coding": [
              {
                "system": "http://hl7.org/fhir/observation-category",
                "code": "procedure"
              }
            ]
          }
        ],
        "code": {
          "coding": [
            {
              "system": "http://loinc.org",
              "code": "19926-5",
              "display": "FEV1/​FVC"
            }
          ],
          "text": "FEV1/​FVC"
        },
        "subject": {
          "reference": "urn:uuid:c7f974eb-e315-44a1-8d70-61fad4c6c6bd"
        },
        "context": {
          "reference": "urn:uuid:b2e22698-ed6d-49b6-9983-80077f2481a8"
        },
        "effectiveDateTime": "2012-08-23T08:31:33-04:00",
        "issued": "2012-08-23T08:31:33-04:00",
        "valueQuantity": {
          "value": 42,
          "unit": "%",
          "system": "http://unitsofmeasure.org/",
          "code": "%"
        },
        "resourceType": "Observation"
      }
    },
    {
      "resource": {
        "meta": {
          "profile": [
            "http://standardhealthrecord.org/fhir/StructureDefinition/shr-procedure-Procedure"
          ]
        },
        "extension": [
          {
            "url": "http://standardhealthrecord.org/fhir/StructureDefinition/shr-core-CodeableConcept-extension",
            "valueCodeableConcept": {
              "coding": [
                {
                  "system": "http://snomed.info/sct",
                  "code": "428191000124101",
                  "display": "Documentation of current medications"
                }
              ],
              "text": "Documentation of current medications"
            }
          }
        ],
        "status": "completed",
        "code": {
          "coding": [
            {
              "system": "http://snomed.info/sct",
              "code": "428191000124101",
              "display": "Documentation of current medications"
            }
          ],
          "text": "Documentation of current medications"
        },
        "subject": {
          "reference": "urn:uuid:c7f974eb-e315-44a1-8d70-61fad4c6c6bd"
        },
        "context": {
          "reference": "urn:uuid:b2e22698-ed6d-49b6-9983-80077f2481a8"
        },
        "performedDateTime": "2012-08-23T08:31:33-04:00",
        "resourceType": "Procedure"
      }
    },
    {
      "resource": {
        "meta": {
          "profile": [
            "http://standardhealthrecord.org/fhir/StructureDefinition/shr-procedure-Procedure"
          ]
        },
        "extension": [
          {
            "url": "http://standardhealthrecord.org/fhir/StructureDefinition/shr-core-CodeableConcept-extension",
            "valueCodeableConcept": {
              "coding": [
                {
                  "system": "http://snomed.info/sct",
                  "code": "127783003",
                  "display": "Spirometry (procedure)"
                }
              ],
              "text": "Spirometry (procedure)"
            }
          }
        ],
        "status": "completed",
        "code": {
          "coding": [
            {
              "system": "http://snomed.info/sct",
              "code": "127783003",
              "display": "Spirometry (procedure)"
            }
          ],
          "text": "Spirometry (procedure)"
        },
        "subject": {
          "reference": "urn:uuid:c7f974eb-e315-44a1-8d70-61fad4c6c6bd"
        },
        "context": {
          "reference": "urn:uuid:b2e22698-ed6d-49b6-9983-80077f2481a8"
        },
        "performedDateTime": "2012-08-23T08:31:33-04:00",
        "reasonReference": {
          "reference": "urn:uuid:2be7881c-89f2-4f8d-a9df-e2d53701c925",
          "display": "Pulmonary emphysema (disorder)"
        },
        "resourceType": "Procedure"
      }
    },
    {
      "resource": {
        "meta": {
          "profile": [
            "http://standardhealthrecord.org/fhir/StructureDefinition/shr-immunization-Immunization"
          ]
        },
        "status": "completed",
        "notGiven": false,
        "vaccineCode": {
          "coding": [
            {
              "system": "http://hl7.org/fhir/sid/cvx",
              "code": "140",
              "display": "Influenza, seasonal, injectable, preservative free"
            }
          ],
          "text": "Influenza, seasonal, injectable, preservative free"
        },
        "patient": {
          "reference": "urn:uuid:c7f974eb-e315-44a1-8d70-61fad4c6c6bd"
        },
        "encounter": {
          "reference": "urn:uuid:b2e22698-ed6d-49b6-9983-80077f2481a8"
        },
        "date": "2012-08-23T08:31:33-04:00",
        "primarySource": true,
        "resourceType": "Immunization"
      }
    },
    {
      "fullUrl": "urn:uuid:bfa75e36-bb83-4466-a298-63c9c2d93ba9",
      "resource": {
        "id": "bfa75e36-bb83-4466-a298-63c9c2d93ba9",
        "meta": {
          "profile": [
            "http://standardhealthrecord.org/fhir/StructureDefinition/shr-encounter-Encounter"
          ]
        },
        "status": "finished",
        "class": {
          "code": "outpatient"
        },
        "type": [
          {
            "coding": [
              {
                "system": "http://snomed.info/sct",
                "code": "698314001"
              }
            ],
            "text": "Consultation for treatment"
          }
        ],
        "subject": {
          "reference": "urn:uuid:c7f974eb-e315-44a1-8d70-61fad4c6c6bd"
        },
        "period": {
          "start": "2014-02-01T17:20:07-05:00",
          "end": "2014-02-01T17:20:07-05:00"
        },
        "serviceProvider": {
          "reference": "urn:uuid:432ec178-094d-436f-8652-b99faac06775"
        },
        "resourceType": "Encounter"
      }
    },
    {
      "fullUrl": "urn:uuid:ead73d67-014e-42d6-8688-0e78351cf5d7",
      "resource": {
        "id": "ead73d67-014e-42d6-8688-0e78351cf5d7",
        "meta": {
          "profile": [
            "http://standardhealthrecord.org/fhir/StructureDefinition/shr-encounter-Encounter"
          ]
        },
        "status": "finished",
        "class": {
          "code": "outpatient"
        },
        "type": [
          {
            "coding": [
              {
                "system": "http://snomed.info/sct",
                "code": "308335008"
              }
            ],
            "text": "Patient encounter procedure"
          }
        ],
        "subject": {
          "reference": "urn:uuid:c7f974eb-e315-44a1-8d70-61fad4c6c6bd"
        },
        "period": {
          "start": "2014-02-16T03:08:55-05:00",
          "end": "2014-02-16T04:17:50-05:00"
        },
        "serviceProvider": {
          "reference": "urn:uuid:432ec178-094d-436f-8652-b99faac06775"
        },
        "resourceType": "Encounter"
      }
    },
    {
      "resource": {
        "meta": {
          "profile": [
            "http://standardhealthrecord.org/fhir/StructureDefinition/shr-procedure-Procedure"
          ]
        },
        "extension": [
          {
            "url": "http://standardhealthrecord.org/fhir/StructureDefinition/shr-core-CodeableConcept-extension",
            "valueCodeableConcept": {
              "coding": [
                {
                  "system": "http://snomed.info/sct",
                  "code": "22523008",
                  "display": "Vasectomy"
                }
              ],
              "text": "Vasectomy"
            }
          }
        ],
        "status": "completed",
        "code": {
          "coding": [
            {
              "system": "http://snomed.info/sct",
              "code": "22523008",
              "display": "Vasectomy"
            }
          ],
          "text": "Vasectomy"
        },
        "subject": {
          "reference": "urn:uuid:c7f974eb-e315-44a1-8d70-61fad4c6c6bd"
        },
        "context": {
          "reference": "urn:uuid:ead73d67-014e-42d6-8688-0e78351cf5d7"
        },
        "performedPeriod": {
          "start": "2014-02-16T03:08:55-05:00",
          "end": "2014-02-16T05:03:48-05:00"
        },
        "resourceType": "Procedure"
      }
    },
    {
      "resource": {
        "status": "completed",
        "category": [
          {
            "coding": [
              {
                "system": "http://snomed.info/sct",
                "code": "787301000000101",
                "display": "Surgery care management"
              }
            ]
          }
        ],
        "subject": {
          "reference": "urn:uuid:c7f974eb-e315-44a1-8d70-61fad4c6c6bd"
        },
        "context": {
          "reference": "urn:uuid:ead73d67-014e-42d6-8688-0e78351cf5d7"
        },
        "period": {
          "start": "2014-02-16",
          "end": "2014-03-01"
        },
        "activity": [
          {
            "detail": {
              "code": {
                "coding": [
                  {
                    "system": "http://snomed.info/sct",
                    "code": "183051005",
                    "display": "Recommendation to rest"
                  }
                ]
              },
              "status": "completed"
            }
          },
          {
            "detail": {
              "code": {
                "coding": [
                  {
                    "system": "http://snomed.info/sct",
                    "code": "243077000",
                    "display": "Recommendation to limit sexual activity"
                  }
                ]
              },
              "status": "completed"
            }
          }
        ],
        "resourceType": "CarePlan"
      }
    },
    {
      "fullUrl": "urn:uuid:c5dc213c-0d99-4650-a50a-47ef8bf1e5fc",
      "resource": {
        "id": "c5dc213c-0d99-4650-a50a-47ef8bf1e5fc",
        "meta": {
          "profile": [
            "http://standardhealthrecord.org/fhir/StructureDefinition/shr-encounter-Encounter"
          ]
        },
        "status": "finished",
        "class": {
          "code": "outpatient"
        },
        "type": [
          {
            "coding": [
              {
                "system": "http://snomed.info/sct",
                "code": "185349003"
              }
            ],
            "text": "Outpatient Encounter"
          }
        ],
        "subject": {
          "reference": "urn:uuid:c7f974eb-e315-44a1-8d70-61fad4c6c6bd"
        },
        "period": {
          "start": "2015-09-20T01:49:02-04:00",
          "end": "2015-09-20T02:49:02-04:00"
        },
        "serviceProvider": {
          "reference": "urn:uuid:432ec178-094d-436f-8652-b99faac06775"
        },
        "resourceType": "Encounter"
      }
    },
    {
      "fullUrl": "urn:uuid:1cd91344-e744-4526-a525-8334bedd505c",
      "resource": {
        "id": "1cd91344-e744-4526-a525-8334bedd505c",
        "meta": {
          "profile": [
            "http://standardhealthrecord.org/fhir/StructureDefinition/shr-observation-Observation",
            "http://standardhealthrecord.org/fhir/StructureDefinition/shr-vital-VitalSign",
            "http://standardhealthrecord.org/fhir/StructureDefinition/shr-vital-BodyHeight"
          ]
        },
        "status": "final",
        "category": [
          {
            "coding": [
              {
                "system": "http://hl7.org/fhir/observation-category",
                "code": "vital-signs"
              }
            ]
          }
        ],
        "code": {
          "coding": [
            {
              "system": "http://loinc.org",
              "code": "8302-2",
              "display": "Body Height"
            }
          ],
          "text": "Body Height"
        },
        "subject": {
          "reference": "urn:uuid:c7f974eb-e315-44a1-8d70-61fad4c6c6bd"
        },
        "context": {
          "reference": "urn:uuid:c5dc213c-0d99-4650-a50a-47ef8bf1e5fc"
        },
        "effectiveDateTime": "2015-09-20T01:49:02-04:00",
        "issued": "2015-09-20T01:49:02-04:00",
        "valueQuantity": {
          "value": 172.77271219700336,
          "unit": "cm",
          "system": "http://unitsofmeasure.org/",
          "code": "cm"
        },
        "resourceType": "Observation"
      }
    },
    {
      "fullUrl": "urn:uuid:23fada4b-ed1b-485a-98b2-03ec7be10731",
      "resource": {
        "id": "23fada4b-ed1b-485a-98b2-03ec7be10731",
        "meta": {
          "profile": [
            "http://standardhealthrecord.org/fhir/StructureDefinition/shr-observation-Observation",
            "http://standardhealthrecord.org/fhir/StructureDefinition/shr-vital-VitalSign",
            "http://standardhealthrecord.org/fhir/StructureDefinition/shr-vital-BodyWeight"
          ]
        },
        "status": "final",
        "category": [
          {
            "coding": [
              {
                "system": "http://hl7.org/fhir/observation-category",
                "code": "vital-signs"
              }
            ]
          }
        ],
        "code": {
          "coding": [
            {
              "system": "http://loinc.org",
              "code": "29463-7",
              "display": "Body Weight"
            }
          ],
          "text": "Body Weight"
        },
        "subject": {
          "reference": "urn:uuid:c7f974eb-e315-44a1-8d70-61fad4c6c6bd"
        },
        "context": {
          "reference": "urn:uuid:c5dc213c-0d99-4650-a50a-47ef8bf1e5fc"
        },
        "effectiveDateTime": "2015-09-20T01:49:02-04:00",
        "issued": "2015-09-20T01:49:02-04:00",
        "valueQuantity": {
          "value": 134.9173322049583,
          "unit": "kg",
          "system": "http://unitsofmeasure.org/",
          "code": "kg"
        },
        "resourceType": "Observation"
      }
    },
    {
      "fullUrl": "urn:uuid:f6e4eee7-7964-414c-8daf-1c40b5a51dbd",
      "resource": {
        "id": "f6e4eee7-7964-414c-8daf-1c40b5a51dbd",
        "meta": {
          "profile": [
            "http://standardhealthrecord.org/fhir/StructureDefinition/shr-observation-Observation",
            "http://standardhealthrecord.org/fhir/StructureDefinition/shr-vital-VitalSign",
            "http://standardhealthrecord.org/fhir/StructureDefinition/shr-vital-BodyMassIndex"
          ]
        },
        "status": "final",
        "category": [
          {
            "coding": [
              {
                "system": "http://hl7.org/fhir/observation-category",
                "code": "vital-signs"
              }
            ]
          }
        ],
        "code": {
          "coding": [
            {
              "system": "http://loinc.org",
              "code": "39156-5",
              "display": "Body Mass Index"
            }
          ],
          "text": "Body Mass Index"
        },
        "subject": {
          "reference": "urn:uuid:c7f974eb-e315-44a1-8d70-61fad4c6c6bd"
        },
        "context": {
          "reference": "urn:uuid:c5dc213c-0d99-4650-a50a-47ef8bf1e5fc"
        },
        "effectiveDateTime": "2015-09-20T01:49:02-04:00",
        "issued": "2015-09-20T01:49:02-04:00",
        "valueQuantity": {
          "value": 45.19781532105894,
          "unit": "kg/m2",
          "system": "http://unitsofmeasure.org/",
          "code": "kg/m2"
        },
        "resourceType": "Observation"
      }
    },
    {
      "fullUrl": "urn:uuid:90be26b5-9627-485a-b0b6-397dd2f2aa1b",
      "resource": {
        "id": "90be26b5-9627-485a-b0b6-397dd2f2aa1b",
        "meta": {
          "profile": [
            "http://standardhealthrecord.org/fhir/StructureDefinition/shr-observation-Observation",
            "http://standardhealthrecord.org/fhir/StructureDefinition/shr-vital-BloodPressure"
          ]
        },
        "status": "final",
        "category": [
          {
            "coding": [
              {
                "system": "http://hl7.org/fhir/observation-category",
                "code": "vital-signs"
              }
            ]
          }
        ],
        "code": {
          "coding": [
            {
              "system": "http://loinc.org",
              "code": "55284-4",
              "display": "Blood Pressure"
            }
          ]
        },
        "subject": {
          "reference": "urn:uuid:c7f974eb-e315-44a1-8d70-61fad4c6c6bd"
        },
        "context": {
          "reference": "urn:uuid:c5dc213c-0d99-4650-a50a-47ef8bf1e5fc"
        },
        "effectiveDateTime": "2015-09-20T01:49:02-04:00",
        "issued": "2015-09-20T01:49:02-04:00",
        "component": [
          {
            "code": {
              "coding": [
                {
                  "system": "http://loinc.org",
                  "code": "8480-6",
                  "display": "Systolic Blood Pressure"
                }
              ],
              "text": "Systolic Blood Pressure"
            },
            "valueQuantity": {
              "value": 121,
              "unit": "mmHg",
              "system": "http://unitsofmeasure.org/",
              "code": "mmHg"
            }
          },
          {
            "code": {
              "coding": [
                {
                  "system": "http://loinc.org",
                  "code": "8462-4",
                  "display": "Diastolic Blood Pressure"
                }
              ],
              "text": "Diastolic Blood Pressure"
            },
            "valueQuantity": {
              "value": 89,
              "unit": "mmHg",
              "system": "http://unitsofmeasure.org/",
              "code": "mmHg"
            }
          }
        ],
        "resourceType": "Observation"
      }
    },
    {
      "fullUrl": "urn:uuid:79cf0400-09b5-4086-9cc0-3e93b0ca00a0",
      "resource": {
        "id": "79cf0400-09b5-4086-9cc0-3e93b0ca00a0",
        "meta": {
          "profile": [
            "http://standardhealthrecord.org/fhir/StructureDefinition/shr-observation-Observation"
          ]
        },
        "status": "final",
        "category": [
          {
            "coding": [
              {
                "system": "http://hl7.org/fhir/observation-category",
                "code": "laboratory"
              }
            ]
          }
        ],
        "code": {
          "coding": [
            {
              "system": "http://loinc.org",
              "code": "2093-3",
              "display": "Total Cholesterol"
            }
          ],
          "text": "Total Cholesterol"
        },
        "subject": {
          "reference": "urn:uuid:c7f974eb-e315-44a1-8d70-61fad4c6c6bd"
        },
        "context": {
          "reference": "urn:uuid:c5dc213c-0d99-4650-a50a-47ef8bf1e5fc"
        },
        "effectiveDateTime": "2015-09-20T01:49:02-04:00",
        "issued": "2015-09-20T01:49:02-04:00",
        "valueQuantity": {
          "value": 192,
          "unit": "mg/dL",
          "system": "http://unitsofmeasure.org/",
          "code": "mg/dL"
        },
        "resourceType": "Observation"
      }
    },
    {
      "fullUrl": "urn:uuid:06e7a426-98cd-4d7a-bbef-d8910659ffa8",
      "resource": {
        "id": "06e7a426-98cd-4d7a-bbef-d8910659ffa8",
        "meta": {
          "profile": [
            "http://standardhealthrecord.org/fhir/StructureDefinition/shr-observation-Observation"
          ]
        },
        "status": "final",
        "category": [
          {
            "coding": [
              {
                "system": "http://hl7.org/fhir/observation-category",
                "code": "laboratory"
              }
            ]
          }
        ],
        "code": {
          "coding": [
            {
              "system": "http://loinc.org",
              "code": "2571-8",
              "display": "Triglycerides"
            }
          ],
          "text": "Triglycerides"
        },
        "subject": {
          "reference": "urn:uuid:c7f974eb-e315-44a1-8d70-61fad4c6c6bd"
        },
        "context": {
          "reference": "urn:uuid:c5dc213c-0d99-4650-a50a-47ef8bf1e5fc"
        },
        "effectiveDateTime": "2015-09-20T01:49:02-04:00",
        "issued": "2015-09-20T01:49:02-04:00",
        "valueQuantity": {
          "value": 127,
          "unit": "mg/dL",
          "system": "http://unitsofmeasure.org/",
          "code": "mg/dL"
        },
        "resourceType": "Observation"
      }
    },
    {
      "fullUrl": "urn:uuid:45d7f247-7b95-4f23-8016-1026fa2e1d06",
      "resource": {
        "id": "45d7f247-7b95-4f23-8016-1026fa2e1d06",
        "meta": {
          "profile": [
            "http://standardhealthrecord.org/fhir/StructureDefinition/shr-observation-Observation"
          ]
        },
        "status": "final",
        "category": [
          {
            "coding": [
              {
                "system": "http://hl7.org/fhir/observation-category",
                "code": "laboratory"
              }
            ]
          }
        ],
        "code": {
          "coding": [
            {
              "system": "http://loinc.org",
              "code": "18262-6",
              "display": "Low Density Lipoprotein Cholesterol"
            }
          ],
          "text": "Low Density Lipoprotein Cholesterol"
        },
        "subject": {
          "reference": "urn:uuid:c7f974eb-e315-44a1-8d70-61fad4c6c6bd"
        },
        "context": {
          "reference": "urn:uuid:c5dc213c-0d99-4650-a50a-47ef8bf1e5fc"
        },
        "effectiveDateTime": "2015-09-20T01:49:02-04:00",
        "issued": "2015-09-20T01:49:02-04:00",
        "valueQuantity": {
          "value": 87,
          "unit": "mg/dL",
          "system": "http://unitsofmeasure.org/",
          "code": "mg/dL"
        },
        "resourceType": "Observation"
      }
    },
    {
      "fullUrl": "urn:uuid:961247d8-314f-455b-b130-86643090df0a",
      "resource": {
        "id": "961247d8-314f-455b-b130-86643090df0a",
        "meta": {
          "profile": [
            "http://standardhealthrecord.org/fhir/StructureDefinition/shr-observation-Observation"
          ]
        },
        "status": "final",
        "category": [
          {
            "coding": [
              {
                "system": "http://hl7.org/fhir/observation-category",
                "code": "laboratory"
              }
            ]
          }
        ],
        "code": {
          "coding": [
            {
              "system": "http://loinc.org",
              "code": "2085-9",
              "display": "High Density Lipoprotein Cholesterol"
            }
          ],
          "text": "High Density Lipoprotein Cholesterol"
        },
        "subject": {
          "reference": "urn:uuid:c7f974eb-e315-44a1-8d70-61fad4c6c6bd"
        },
        "context": {
          "reference": "urn:uuid:c5dc213c-0d99-4650-a50a-47ef8bf1e5fc"
        },
        "effectiveDateTime": "2015-09-20T01:49:02-04:00",
        "issued": "2015-09-20T01:49:02-04:00",
        "valueQuantity": {
          "value": 79,
          "unit": "mg/dL",
          "system": "http://unitsofmeasure.org/",
          "code": "mg/dL"
        },
        "resourceType": "Observation"
      }
    },
    {
      "fullUrl": "urn:uuid:80b5dc0e-b414-45b1-a4ad-035704170ea9",
      "resource": {
        "id": "80b5dc0e-b414-45b1-a4ad-035704170ea9",
        "meta": {
          "profile": [
            "http://standardhealthrecord.org/fhir/StructureDefinition/shr-observation-Panel"
          ]
        },
        "status": "final",
        "code": {
          "coding": [
            {
              "system": "http://loinc.org",
              "code": "57698-3",
              "display": "Lipid Panel"
            }
          ]
        },
        "subject": {
          "reference": "urn:uuid:c7f974eb-e315-44a1-8d70-61fad4c6c6bd"
        },
        "context": {
          "reference": "urn:uuid:c5dc213c-0d99-4650-a50a-47ef8bf1e5fc"
        },
        "effectiveDateTime": "2015-09-20T01:49:02-04:00",
        "issued": "2015-09-20T01:49:02-04:00",
        "result": [
          {
            "reference": "urn:uuid:79cf0400-09b5-4086-9cc0-3e93b0ca00a0",
            "display": "Total Cholesterol"
          },
          {
            "reference": "urn:uuid:06e7a426-98cd-4d7a-bbef-d8910659ffa8",
            "display": "Triglycerides"
          },
          {
            "reference": "urn:uuid:45d7f247-7b95-4f23-8016-1026fa2e1d06",
            "display": "Low Density Lipoprotein Cholesterol"
          },
          {
            "reference": "urn:uuid:961247d8-314f-455b-b130-86643090df0a",
            "display": "High Density Lipoprotein Cholesterol"
          }
        ],
        "resourceType": "DiagnosticReport"
      }
    },
    {
      "fullUrl": "urn:uuid:07322246-8601-4061-8a1f-f1ed7a63371e",
      "resource": {
        "id": "07322246-8601-4061-8a1f-f1ed7a63371e",
        "meta": {
          "profile": [
            "http://standardhealthrecord.org/fhir/StructureDefinition/shr-observation-Observation"
          ]
        },
        "status": "final",
        "category": [
          {
            "coding": [
              {
                "system": "http://hl7.org/fhir/observation-category",
                "code": "procedure"
              }
            ]
          }
        ],
        "code": {
          "coding": [
            {
              "system": "http://loinc.org",
              "code": "19926-5",
              "display": "FEV1/​FVC"
            }
          ],
          "text": "FEV1/​FVC"
        },
        "subject": {
          "reference": "urn:uuid:c7f974eb-e315-44a1-8d70-61fad4c6c6bd"
        },
        "context": {
          "reference": "urn:uuid:c5dc213c-0d99-4650-a50a-47ef8bf1e5fc"
        },
        "effectiveDateTime": "2015-09-20T01:49:02-04:00",
        "issued": "2015-09-20T01:49:02-04:00",
        "valueQuantity": {
          "value": 36,
          "unit": "%",
          "system": "http://unitsofmeasure.org/",
          "code": "%"
        },
        "resourceType": "Observation"
      }
    },
    {
      "resource": {
        "meta": {
          "profile": [
            "http://standardhealthrecord.org/fhir/StructureDefinition/shr-procedure-Procedure"
          ]
        },
        "extension": [
          {
            "url": "http://standardhealthrecord.org/fhir/StructureDefinition/shr-core-CodeableConcept-extension",
            "valueCodeableConcept": {
              "coding": [
                {
                  "system": "http://snomed.info/sct",
                  "code": "127783003",
                  "display": "Spirometry (procedure)"
                }
              ],
              "text": "Spirometry (procedure)"
            }
          }
        ],
        "status": "completed",
        "code": {
          "coding": [
            {
              "system": "http://snomed.info/sct",
              "code": "127783003",
              "display": "Spirometry (procedure)"
            }
          ],
          "text": "Spirometry (procedure)"
        },
        "subject": {
          "reference": "urn:uuid:c7f974eb-e315-44a1-8d70-61fad4c6c6bd"
        },
        "context": {
          "reference": "urn:uuid:c5dc213c-0d99-4650-a50a-47ef8bf1e5fc"
        },
        "performedDateTime": "2015-09-20T01:49:02-04:00",
        "reasonReference": {
          "reference": "urn:uuid:2be7881c-89f2-4f8d-a9df-e2d53701c925",
          "display": "Pulmonary emphysema (disorder)"
        },
        "resourceType": "Procedure"
      }
    },
    {
      "resource": {
        "meta": {
          "profile": [
            "http://standardhealthrecord.org/fhir/StructureDefinition/shr-immunization-Immunization"
          ]
        },
        "status": "completed",
        "notGiven": false,
        "vaccineCode": {
          "coding": [
            {
              "system": "http://hl7.org/fhir/sid/cvx",
              "code": "140",
              "display": "Influenza, seasonal, injectable, preservative free"
            }
          ],
          "text": "Influenza, seasonal, injectable, preservative free"
        },
        "patient": {
          "reference": "urn:uuid:c7f974eb-e315-44a1-8d70-61fad4c6c6bd"
        },
        "encounter": {
          "reference": "urn:uuid:c5dc213c-0d99-4650-a50a-47ef8bf1e5fc"
        },
        "date": "2015-09-20T01:49:02-04:00",
        "primarySource": true,
        "resourceType": "Immunization"
      }
    },
    {
      "resource": {
        "meta": {
          "profile": [
            "http://standardhealthrecord.org/fhir/StructureDefinition/shr-immunization-Immunization"
          ]
        },
        "status": "completed",
        "notGiven": false,
        "vaccineCode": {
          "coding": [
            {
              "system": "http://hl7.org/fhir/sid/cvx",
              "code": "113",
              "display": "Td (adult) preservative free"
            }
          ],
          "text": "Td (adult) preservative free"
        },
        "patient": {
          "reference": "urn:uuid:c7f974eb-e315-44a1-8d70-61fad4c6c6bd"
        },
        "encounter": {
          "reference": "urn:uuid:c5dc213c-0d99-4650-a50a-47ef8bf1e5fc"
        },
        "date": "2015-09-20T01:49:02-04:00",
        "primarySource": true,
        "resourceType": "Immunization"
      }
    },
    {
      "fullUrl": "urn:uuid:5a9432ae-f2e8-432c-8fc9-9ea3fe66bbc1",
      "resource": {
        "id": "5a9432ae-f2e8-432c-8fc9-9ea3fe66bbc1",
        "meta": {
          "profile": [
            "http://standardhealthrecord.org/fhir/StructureDefinition/shr-encounter-Encounter"
          ]
        },
        "status": "finished",
        "class": {
          "code": "ambulatory"
        },
        "type": [
          {
            "coding": [
              {
                "system": "http://snomed.info/sct",
                "code": "185345009"
              }
            ],
            "text": "Encounter for symptom"
          }
        ],
        "subject": {
          "reference": "urn:uuid:c7f974eb-e315-44a1-8d70-61fad4c6c6bd"
        },
        "period": {
          "start": "2016-03-15T14:37:36-04:00",
          "end": "2016-03-15T14:37:36-04:00"
        },
        "reason": {
          "coding": [
            {
              "system": "http://snomed.info/sct",
              "code": "444814009",
              "display": "Viral sinusitis (disorder)"
            }
          ]
        },
        "serviceProvider": {
          "reference": "urn:uuid:432ec178-094d-436f-8652-b99faac06775"
        },
        "resourceType": "Encounter"
      }
    },
    {
      "fullUrl": "urn:uuid:cfe5649c-bdd0-4c20-a7e6-bccb25edf17a",
      "resource": {
        "id": "cfe5649c-bdd0-4c20-a7e6-bccb25edf17a",
        "meta": {
          "profile": [
            "http://standardhealthrecord.org/fhir/StructureDefinition/shr-problem-Problem"
          ]
        },
        "clinicalStatus": "active",
        "verificationStatus": "confirmed",
        "code": {
          "coding": [
            {
              "system": "http://snomed.info/sct",
              "code": "444814009",
              "display": "Viral sinusitis (disorder)"
            }
          ],
          "text": "Viral sinusitis (disorder)"
        },
        "subject": {
          "reference": "urn:uuid:c7f974eb-e315-44a1-8d70-61fad4c6c6bd"
        },
        "context": {
          "reference": "urn:uuid:5a9432ae-f2e8-432c-8fc9-9ea3fe66bbc1"
        },
        "onsetDateTime": "2016-03-07T05:06:47-05:00",
        "abatementDateTime": "2016-04-06T22:58:53-04:00",
        "assertedDate": "2016-03-07",
        "resourceType": "Condition"
      }
    },
    {
      "fullUrl": "urn:uuid:83086528-740e-4675-a202-bdfd86b0244e",
      "resource": {
        "id": "83086528-740e-4675-a202-bdfd86b0244e",
        "meta": {
          "profile": [
            "http://standardhealthrecord.org/fhir/StructureDefinition/shr-observation-Observation"
          ]
        },
        "status": "final",
        "category": [
          {
            "coding": [
              {
                "system": "http://hl7.org/fhir/observation-category",
                "code": "survey"
              }
            ]
          }
        ],
        "code": {
          "coding": [
            {
              "system": "http://snomed.info/sct",
              "code": "273724008",
              "display": "Quality adjusted life years"
            }
          ],
          "text": "Quality adjusted life years"
        },
        "subject": {
          "reference": "urn:uuid:c7f974eb-e315-44a1-8d70-61fad4c6c6bd"
        },
        "effectiveDateTime": "2017-10-06T22:39:41-04:00",
        "issued": "2017-10-06T22:39:41-04:00",
        "valueQuantity": {
          "value": 43.7441539433121,
          "unit": "years",
          "system": "http://unitsofmeasure.org/",
          "code": "years"
        },
        "resourceType": "Observation"
      }
    },
    {
      "fullUrl": "urn:uuid:afb783b7-858e-473a-9205-cecff0203f7e",
      "resource": {
        "id": "afb783b7-858e-473a-9205-cecff0203f7e",
        "meta": {
          "profile": [
            "http://standardhealthrecord.org/fhir/StructureDefinition/shr-observation-Observation"
          ]
        },
        "status": "final",
        "category": [
          {
            "coding": [
              {
                "system": "http://hl7.org/fhir/observation-category",
                "code": "survey"
              }
            ]
          }
        ],
        "code": {
          "coding": [
            {
              "system": "http://snomed.info/sct",
              "code": "273421001",
              "display": "Disability rating scale"
            }
          ],
          "text": "Disability rating scale"
        },
        "subject": {
          "reference": "urn:uuid:c7f974eb-e315-44a1-8d70-61fad4c6c6bd"
        },
        "effectiveDateTime": "2017-10-06T22:39:41-04:00",
        "issued": "2017-10-06T22:39:41-04:00",
        "valueQuantity": {
          "value": 0.25584605668790145,
          "unit": "years",
          "system": "http://unitsofmeasure.org/",
          "code": "years"
        },
        "resourceType": "Observation"
      }
    }
  ],
  "resourceType": "Bundle"
}