{
  "type": "collection",
  "entry": [
    {
      "fullUrl": "urn:uuid:7aa12bb3-7309-4ffc-8d75-a8cbc95cb79e",
      "resource": {
        "id": "7aa12bb3-7309-4ffc-8d75-a8cbc95cb79e",
        "meta": {
          "profile": [
            "http://standardhealthrecord.org/fhir/StructureDefinition/shr-actor-Organization"
          ]
        },
        "type": [
          {
            "coding": [
              {
                "system": "http://hl7.org/fhir/ValueSet/organization-type",
                "code": "prov",
                "display": "Healthcare Provider"
              }
            ],
            "text": "Healthcare Provider"
          }
        ],
        "name": "TEWKSBURY HOSPITAL",
        "resourceType": "Organization"
      }
    },
    {
      "fullUrl": "urn:uuid:85bc8c3a-470f-46b2-ba9f-4e3d69220352",
      "resource": {
        "id": "85bc8c3a-470f-46b2-ba9f-4e3d69220352",
        "meta": {
          "profile": [
            "http://standardhealthrecord.org/fhir/StructureDefinition/shr-demographics-PersonOfRecord"
          ]
        },
        "text": {
          "status": "generated",
          "div": "<div xmlns=\"http://www.w3.org/1999/xhtml\">Generated by <a href=\"https://github.com/synthetichealth/synthea\">Synthea</a>. Version identifier: 01d01d675c68502483be0eb37fb293bba5371d7f</div>"
        },
        "extension": [
          {
            "url": "http://hl7.org/fhir/us/core/StructureDefinition/us-core-race",
            "valueCodeableConcept": {
              "coding": [
                {
                  "system": "http://hl7.org/fhir/v3/Race",
                  "code": "2106-3",
                  "display": "White"
                }
              ],
              "text": "race"
            }
          },
          {
            "url": "http://hl7.org/fhir/us/core/StructureDefinition/us-core-ethnicity",
            "valueCodeableConcept": {
              "coding": [
                {
                  "system": "http://hl7.org/fhir/v3/Ethnicity",
                  "code": "2186-5",
                  "display": "Nonhispanic"
                }
              ],
              "text": "ethnicity"
            }
          },
          {
            "url": "http://hl7.org/fhir/StructureDefinition/birthPlace",
            "valueAddress": {
              "city": "Ludlow",
              "state": "MA",
              "country": "US"
            }
          },
          {
            "url": "http://hl7.org/fhir/StructureDefinition/patient-mothersMaidenName",
            "valueString": "Rosa572 Fisher523"
          },
          {
            "url": "http://hl7.org/fhir/us/core/StructureDefinition/us-core-birthsex",
            "valueCode": "F"
          },
          {
            "url": "http://hl7.org/fhir/StructureDefinition/patient-interpreterRequired",
            "valueBoolean": false
          },
          {
            "url": "http://standardhealthrecord.org/fhir/StructureDefinition/shr-actor-FictionalPerson-extension",
            "valueBoolean": true
          },
          {
            "url": "http://standardhealthrecord.org/fhir/StructureDefinition/shr-demographics-FathersName-extension",
            "valueHumanName": {
              "text": "Cornell62 Weimann532"
            }
          },
          {
            "url": "http://standardhealthrecord.org/fhir/StructureDefinition/shr-demographics-SocialSecurityNumber-extension",
            "valueString": "999-64-9292"
          }
        ],
        "identifier": [
          {
            "system": "https://github.com/synthetichealth/synthea",
            "value": "eb3ce2cc-3650-48aa-8770-1299898058f8"
          },
          {
            "type": {
              "coding": [
                {
                  "system": "http://hl7.org/fhir/identifier-type",
                  "code": "SB"
                }
              ]
            },
            "system": "http://hl7.org/fhir/sid/us-ssn",
            "value": "999649292"
          },
          {
            "type": {
              "coding": [
                {
                  "system": "http://hl7.org/fhir/v2/0203",
                  "code": "DL"
                }
              ]
            },
            "system": "urn:oid:2.16.840.1.113883.4.3.25",
            "value": "S99990690"
          },
          {
            "type": {
              "coding": [
                {
                  "system": "http://hl7.org/fhir/v2/0203",
                  "code": "PPN"
                }
              ]
            },
            "system": "http://standardhealthrecord.org/fhir/StructureDefinition/passportNumber",
            "value": "X41360302X"
          },
          {
            "type": {
              "coding": [
                {
                  "system": "http://hl7.org/fhir/v2/0203",
                  "code": "MR"
                }
              ]
            },
            "system": "http://hospital.smarthealthit.org",
            "value": "eb3ce2cc-3650-48aa-8770-1299898058f8"
          }
        ],
        "name": [
          {
            "use": "official",
            "family": "Weimann532",
            "given": [
              "Brian465"
            ],
            "prefix": [
              "Ms."
            ],
            "suffix": [
              "PhD"
            ]
          }
        ],
        "telecom": [
          {
            "system": "phone",
            "value": "1-922-162-8065",
            "use": "home"
          }
        ],
        "gender": "female",
        "birthDate": "1940-04-26",
        "deceasedDateTime": "1990-12-20T15:16:17-05:00",
        "address": [
          {
            "extension": [
              {
                "extension": [
                  {
                    "url": "latitude",
                    "valueDecimal": 42.56705737179378
                  },
                  {
                    "url": "longitude",
                    "valueDecimal": -71.21591015039107
                  }
                ],
                "url": "http://hl7.org/fhir/StructureDefinition/geolocation"
              }
            ],
            "line": [
              "201 Gleason Drive"
            ],
            "city": "Billerica",
            "state": "MA",
            "postalCode": "01822",
            "country": "US"
          }
        ],
        "maritalStatus": {
          "coding": [
            {
              "system": "http://hl7.org/fhir/v3/MaritalStatus",
              "code": "S"
            }
          ],
          "text": "S"
        },
        "multipleBirthBoolean": false,
        "communication": [
          {
            "language": {
              "coding": [
                {
                  "system": "http://hl7.org/fhir/ValueSet/languages",
                  "code": "en-US",
                  "display": "English (United States)"
                }
              ]
            }
          }
        ],
        "generalPractitioner": [
          {
            "reference": "urn:uuid:7aa12bb3-7309-4ffc-8d75-a8cbc95cb79e"
          }
        ],
        "resourceType": "Patient"
      }
    },
    {
      "fullUrl": "urn:uuid:aed3dab6-227d-4de1-93e6-7488d6661515",
      "resource": {
        "id": "aed3dab6-227d-4de1-93e6-7488d6661515",
        "meta": {
          "profile": [
            "http://standardhealthrecord.org/fhir/StructureDefinition/shr-encounter-Encounter"
          ]
        },
        "status": "finished",
        "class": {
          "code": "ambulatory"
        },
        "type": [
          {
            "coding": [
              {
                "system": "http://snomed.info/sct",
                "code": "308646001"
              }
            ],
            "text": "Death Certification"
          }
        ],
        "subject": {
          "reference": "urn:uuid:85bc8c3a-470f-46b2-ba9f-4e3d69220352"
        },
        "period": {
          "start": "1990-12-20T15:16:17-05:00",
          "end": "1990-12-20T15:31:17-05:00"
        },
        "serviceProvider": {
          "reference": "urn:uuid:7aa12bb3-7309-4ffc-8d75-a8cbc95cb79e"
        },
        "resourceType": "Encounter"
      }
    },
    {
      "fullUrl": "urn:uuid:2e6a8ec5-405b-419b-b677-41d2b7e26b93",
      "resource": {
        "id": "2e6a8ec5-405b-419b-b677-41d2b7e26b93",
        "meta": {
          "profile": [
            "http://standardhealthrecord.org/fhir/StructureDefinition/shr-problem-Problem"
          ]
        },
        "clinicalStatus": "active",
        "verificationStatus": "confirmed",
        "code": {
          "coding": [
            {
              "system": "http://snomed.info/sct",
              "code": "38341003",
              "display": "Hypertension"
            }
          ],
          "text": "Hypertension"
        },
        "subject": {
          "reference": "urn:uuid:85bc8c3a-470f-46b2-ba9f-4e3d69220352"
        },
        "context": {
          "reference": "urn:uuid:aed3dab6-227d-4de1-93e6-7488d6661515"
        },
        "onsetDateTime": "1958-10-10T00:10:44-04:00",
        "assertedDate": "1958-10-10",
        "resourceType": "Condition"
      }
    },
    {
      "fullUrl": "urn:uuid:be04a744-2d9e-4c40-a353-0510f6e979f9",
      "resource": {
        "id": "be04a744-2d9e-4c40-a353-0510f6e979f9",
        "meta": {
          "profile": [
            "http://standardhealthrecord.org/fhir/StructureDefinition/shr-problem-Problem"
          ]
        },
        "clinicalStatus": "active",
        "verificationStatus": "confirmed",
        "code": {
          "coding": [
            {
              "system": "http://snomed.info/sct",
              "code": "44054006",
              "display": "Diabetes"
            }
          ],
          "text": "Diabetes"
        },
        "subject": {
          "reference": "urn:uuid:85bc8c3a-470f-46b2-ba9f-4e3d69220352"
        },
        "context": {
          "reference": "urn:uuid:aed3dab6-227d-4de1-93e6-7488d6661515"
        },
        "onsetDateTime": "1963-08-09T02:58:56-04:00",
        "assertedDate": "1963-08-09",
        "resourceType": "Condition"
      }
    },
    {
      "fullUrl": "urn:uuid:0f450f26-18ea-4c69-b6f5-a1a70398120b",
      "resource": {
        "id": "0f450f26-18ea-4c69-b6f5-a1a70398120b",
        "meta": {
          "profile": [
            "http://standardhealthrecord.org/fhir/StructureDefinition/shr-problem-Problem"
          ]
        },
        "clinicalStatus": "active",
        "verificationStatus": "confirmed",
        "code": {
          "coding": [
            {
              "system": "http://snomed.info/sct",
              "code": "422034002",
              "display": "Diabetic retinopathy associated with type II diabetes mellitus (disorder)"
            }
          ],
          "text": "Diabetic retinopathy associated with type II diabetes mellitus (disorder)"
        },
        "subject": {
          "reference": "urn:uuid:85bc8c3a-470f-46b2-ba9f-4e3d69220352"
        },
        "context": {
          "reference": "urn:uuid:aed3dab6-227d-4de1-93e6-7488d6661515"
        },
        "onsetDateTime": "1963-08-09T02:58:56-04:00",
        "assertedDate": "1963-08-09",
        "resourceType": "Condition"
      }
    },
    {
      "fullUrl": "urn:uuid:d8ec0505-f97b-473d-973a-1afa4255d34e",
      "resource": {
        "id": "d8ec0505-f97b-473d-973a-1afa4255d34e",
        "meta": {
          "profile": [
            "http://standardhealthrecord.org/fhir/StructureDefinition/shr-problem-Problem"
          ]
        },
        "clinicalStatus": "active",
        "verificationStatus": "confirmed",
        "code": {
          "coding": [
            {
              "system": "http://snomed.info/sct",
              "code": "40055000",
              "display": "Chronic sinusitis (disorder)"
            }
          ],
          "text": "Chronic sinusitis (disorder)"
        },
        "subject": {
          "reference": "urn:uuid:85bc8c3a-470f-46b2-ba9f-4e3d69220352"
        },
        "context": {
          "reference": "urn:uuid:aed3dab6-227d-4de1-93e6-7488d6661515"
        },
        "onsetDateTime": "1974-07-11T22:13:27-04:00",
        "assertedDate": "1974-07-11",
        "resourceType": "Condition"
      }
    },
    {
      "fullUrl": "urn:uuid:4a95fac2-858c-4d1d-824f-c871c8b6b5e8",
      "resource": {
        "id": "4a95fac2-858c-4d1d-824f-c871c8b6b5e8",
        "meta": {
          "profile": [
            "http://standardhealthrecord.org/fhir/StructureDefinition/shr-problem-Problem"
          ]
        },
        "clinicalStatus": "active",
        "verificationStatus": "confirmed",
        "code": {
          "coding": [
            {
              "system": "http://snomed.info/sct",
              "code": "1551000119108",
              "display": "Nonproliferative diabetic retinopathy due to type 2 diabetes mellitus (disorder)"
            }
          ],
          "text": "Nonproliferative diabetic retinopathy due to type 2 diabetes mellitus (disorder)"
        },
        "subject": {
          "reference": "urn:uuid:85bc8c3a-470f-46b2-ba9f-4e3d69220352"
        },
        "context": {
          "reference": "urn:uuid:aed3dab6-227d-4de1-93e6-7488d6661515"
        },
        "onsetDateTime": "1976-05-30T02:13:58-04:00",
        "assertedDate": "1976-05-30",
        "resourceType": "Condition"
      }
    },
    {
      "fullUrl": "urn:uuid:bada58cd-49b1-48df-a70e-c7c65a1b0638",
      "resource": {
        "id": "bada58cd-49b1-48df-a70e-c7c65a1b0638",
        "meta": {
          "profile": [
            "http://standardhealthrecord.org/fhir/StructureDefinition/shr-problem-Problem"
          ]
        },
        "clinicalStatus": "active",
        "verificationStatus": "confirmed",
        "code": {
          "coding": [
            {
              "system": "http://snomed.info/sct",
              "code": "1501000119109",
              "display": "Proliferative diabetic retinopathy due to type II diabetes mellitus (disorder)"
            }
          ],
          "text": "Proliferative diabetic retinopathy due to type II diabetes mellitus (disorder)"
        },
        "subject": {
          "reference": "urn:uuid:85bc8c3a-470f-46b2-ba9f-4e3d69220352"
        },
        "context": {
          "reference": "urn:uuid:aed3dab6-227d-4de1-93e6-7488d6661515"
        },
        "onsetDateTime": "1979-06-25T21:25:18-04:00",
        "assertedDate": "1979-06-25",
        "resourceType": "Condition"
      }
    },
    {
      "fullUrl": "urn:uuid:35787b42-4559-46a1-9a2c-b3d8d233cbcf",
      "resource": {
        "id": "35787b42-4559-46a1-9a2c-b3d8d233cbcf",
        "meta": {
          "profile": [
            "http://standardhealthrecord.org/fhir/StructureDefinition/shr-problem-Problem"
          ]
        },
        "clinicalStatus": "active",
        "verificationStatus": "confirmed",
        "code": {
          "coding": [
            {
              "system": "http://snomed.info/sct",
              "code": "15777000",
              "display": "Prediabetes"
            }
          ],
          "text": "Prediabetes"
        },
        "subject": {
          "reference": "urn:uuid:85bc8c3a-470f-46b2-ba9f-4e3d69220352"
        },
        "context": {
          "reference": "urn:uuid:aed3dab6-227d-4de1-93e6-7488d6661515"
        },
        "onsetDateTime": "1980-06-27T18:26:43-04:00",
        "assertedDate": "1980-06-27",
        "resourceType": "Condition"
      }
    },
    {
      "fullUrl": "urn:uuid:99a406a5-cc57-412f-8a7c-c794b500532a",
      "resource": {
        "id": "99a406a5-cc57-412f-8a7c-c794b500532a",
        "meta": {
          "profile": [
            "http://standardhealthrecord.org/fhir/StructureDefinition/shr-problem-Problem"
          ]
        },
        "clinicalStatus": "active",
        "verificationStatus": "confirmed",
        "code": {
          "coding": [
            {
              "system": "http://snomed.info/sct",
              "code": "97331000119101",
              "display": "Macular edema and retinopathy due to type 2 diabetes mellitus (disorder)"
            }
          ],
          "text": "Macular edema and retinopathy due to type 2 diabetes mellitus (disorder)"
        },
        "subject": {
          "reference": "urn:uuid:85bc8c3a-470f-46b2-ba9f-4e3d69220352"
        },
        "context": {
          "reference": "urn:uuid:aed3dab6-227d-4de1-93e6-7488d6661515"
        },
        "onsetDateTime": "1988-08-22T08:32:38-04:00",
        "assertedDate": "1988-08-22",
        "resourceType": "Condition"
      }
    },
    {
      "fullUrl": "urn:uuid:07c09c96-a9c1-48d8-9d33-9bbc292efa12",
      "resource": {
        "id": "07c09c96-a9c1-48d8-9d33-9bbc292efa12",
        "meta": {
          "profile": [
            "http://standardhealthrecord.org/fhir/StructureDefinition/shr-problem-Problem"
          ]
        },
        "clinicalStatus": "active",
        "verificationStatus": "confirmed",
        "code": {
          "coding": [
            {
              "system": "http://snomed.info/sct",
              "code": "162573006",
              "display": "Suspected lung cancer (situation)"
            }
          ],
          "text": "Suspected lung cancer (situation)"
        },
        "subject": {
          "reference": "urn:uuid:85bc8c3a-470f-46b2-ba9f-4e3d69220352"
        },
        "context": {
          "reference": "urn:uuid:aed3dab6-227d-4de1-93e6-7488d6661515"
        },
        "onsetDateTime": "1990-03-09T06:15:51-05:00",
        "assertedDate": "1990-03-09",
        "resourceType": "Condition"
      }
    },
    {
      "fullUrl": "urn:uuid:d683c099-0b73-4639-a13b-e4c6a5482899",
      "resource": {
        "id": "d683c099-0b73-4639-a13b-e4c6a5482899",
        "meta": {
          "profile": [
            "http://standardhealthrecord.org/fhir/StructureDefinition/shr-problem-Problem"
          ]
        },
        "clinicalStatus": "active",
        "verificationStatus": "confirmed",
        "code": {
          "coding": [
            {
              "system": "http://snomed.info/sct",
              "code": "254632001",
              "display": "Small cell carcinoma of lung (disorder)"
            }
          ],
          "text": "Small cell carcinoma of lung (disorder)"
        },
        "subject": {
          "reference": "urn:uuid:85bc8c3a-470f-46b2-ba9f-4e3d69220352"
        },
        "context": {
          "reference": "urn:uuid:aed3dab6-227d-4de1-93e6-7488d6661515"
        },
        "onsetDateTime": "1990-03-18T09:06:41-05:00",
        "assertedDate": "1990-03-18",
        "resourceType": "Condition"
      }
    },
    {
      "fullUrl": "urn:uuid:84b7b4de-a990-4802-bef3-146d09a2da94",
      "resource": {
        "id": "84b7b4de-a990-4802-bef3-146d09a2da94",
        "meta": {
          "profile": [
            "http://standardhealthrecord.org/fhir/StructureDefinition/shr-problem-Problem"
          ]
        },
        "clinicalStatus": "active",
        "verificationStatus": "confirmed",
        "code": {
          "coding": [
            {
              "system": "http://snomed.info/sct",
              "code": "67841000119103",
              "display": "Primary small cell malignant neoplasm of lung, TNM stage 4 (disorder)"
            }
          ],
          "text": "Primary small cell malignant neoplasm of lung, TNM stage 4 (disorder)"
        },
        "subject": {
          "reference": "urn:uuid:85bc8c3a-470f-46b2-ba9f-4e3d69220352"
        },
        "context": {
          "reference": "urn:uuid:aed3dab6-227d-4de1-93e6-7488d6661515"
        },
        "onsetDateTime": "1990-03-20T06:28:11-05:00",
        "assertedDate": "1990-03-20",
        "resourceType": "Condition"
      }
    },
    {
      "fullUrl": "urn:uuid:ccccff6d-2254-4f7c-ab83-f1bcc4e98016",
      "resource": {
        "id": "ccccff6d-2254-4f7c-ab83-f1bcc4e98016",
        "meta": {
          "profile": [
            "http://standardhealthrecord.org/fhir/StructureDefinition/shr-observation-Observation"
          ]
        },
        "status": "final",
        "category": [
          {
            "coding": [
              {
                "system": "http://hl7.org/fhir/observation-category"
              }
            ]
          }
        ],
        "code": {
          "coding": [
            {
              "system": "http://loinc.org",
              "code": "69453-9",
              "display": "Cause of Death [US Standard Certificate of Death]"
            }
          ],
          "text": "Cause of Death [US Standard Certificate of Death]"
        },
        "subject": {
          "reference": "urn:uuid:85bc8c3a-470f-46b2-ba9f-4e3d69220352"
        },
        "context": {
          "reference": "urn:uuid:aed3dab6-227d-4de1-93e6-7488d6661515"
        },
        "effectiveDateTime": "1990-12-20T15:16:17-05:00",
        "issued": "1990-12-20T15:16:17-05:00",
        "valueCodeableConcept": {
          "coding": [
            {
              "system": "http://snomed.info/sct",
              "code": "254632001",
              "display": "Small cell carcinoma of lung (disorder)"
            }
          ],
          "text": "Small cell carcinoma of lung (disorder)"
        },
        "resourceType": "Observation"
      }
    },
    {
      "fullUrl": "urn:uuid:e07f23e6-0255-4d91-9a25-b1af69c42ae3",
      "resource": {
        "id": "e07f23e6-0255-4d91-9a25-b1af69c42ae3",
        "meta": {
          "profile": [
            "http://standardhealthrecord.org/fhir/StructureDefinition/shr-observation-Panel"
          ]
        },
        "status": "final",
        "code": {
          "coding": [
            {
              "system": "http://loinc.org",
              "code": "69409-1",
              "display": "U.S. standard certificate of death - 2003 revision"
            }
          ]
        },
        "subject": {
          "reference": "urn:uuid:85bc8c3a-470f-46b2-ba9f-4e3d69220352"
        },
        "context": {
          "reference": "urn:uuid:aed3dab6-227d-4de1-93e6-7488d6661515"
        },
        "effectiveDateTime": "1990-12-20T15:16:17-05:00",
        "issued": "1990-12-20T15:16:17-05:00",
        "result": [
          {
            "reference": "urn:uuid:ccccff6d-2254-4f7c-ab83-f1bcc4e98016",
            "display": "Cause of Death [US Standard Certificate of Death]"
          }
        ],
        "resourceType": "DiagnosticReport"
      }
    },
    {
      "fullUrl": "urn:uuid:0167b972-465a-4047-9c0a-cef804548645",
      "resource": {
        "id": "0167b972-465a-4047-9c0a-cef804548645",
        "status": "in-progress",
        "description": {
          "text": "Hemoglobin A1c total in Blood < 7.0"
        },
        "addresses": [
          {
            "reference": "urn:uuid:be04a744-2d9e-4c40-a353-0510f6e979f9"
          }
        ],
        "resourceType": "Goal"
      }
    },
    {
      "fullUrl": "urn:uuid:fb8a8498-41a1-4f1e-88eb-a2fc54d4100a",
      "resource": {
        "id": "fb8a8498-41a1-4f1e-88eb-a2fc54d4100a",
        "status": "in-progress",
        "description": {
          "text": "Glucose [Mass/volume] in Blood < 108"
        },
        "addresses": [
          {
            "reference": "urn:uuid:be04a744-2d9e-4c40-a353-0510f6e979f9"
          }
        ],
        "resourceType": "Goal"
      }
    },
    {
      "fullUrl": "urn:uuid:02cf1ed7-7f4f-4b9e-aea4-c7b9f48ed336",
      "resource": {
        "id": "02cf1ed7-7f4f-4b9e-aea4-c7b9f48ed336",
        "status": "in-progress",
        "description": {
          "text": "Maintain blood pressure below 140/90 mmHg"
        },
        "addresses": [
          {
            "reference": "urn:uuid:be04a744-2d9e-4c40-a353-0510f6e979f9"
          }
        ],
        "resourceType": "Goal"
      }
    },
    {
      "fullUrl": "urn:uuid:af3a5193-deb6-4ae2-a45e-ac2c2f0c2793",
      "resource": {
        "id": "af3a5193-deb6-4ae2-a45e-ac2c2f0c2793",
        "status": "in-progress",
        "description": {
          "text": "Improve and maintenance of optimal foot health: aim at early detection of peripheral vascular problems and neuropathy presumed due to diabetes; and prevention of diabetic foot ulcer, gangrene"
        },
        "addresses": [
          {
            "reference": "urn:uuid:be04a744-2d9e-4c40-a353-0510f6e979f9"
          }
        ],
        "resourceType": "Goal"
      }
    },
    {
      "fullUrl": "urn:uuid:0889eeb5-7fa0-4d1d-bf45-bcd2b93498fc",
      "resource": {
        "id": "0889eeb5-7fa0-4d1d-bf45-bcd2b93498fc",
        "status": "in-progress",
        "description": {
          "text": "Address patient knowledge deficit on diabetic self-care"
        },
        "addresses": [
          {
            "reference": "urn:uuid:be04a744-2d9e-4c40-a353-0510f6e979f9"
          }
        ],
        "resourceType": "Goal"
      }
    },
    {
      "resource": {
        "status": "active",
        "category": [
          {
            "coding": [
              {
                "system": "http://snomed.info/sct",
                "code": "698360004",
                "display": "Diabetes self management plan"
              }
            ]
          }
        ],
        "subject": {
          "reference": "urn:uuid:85bc8c3a-470f-46b2-ba9f-4e3d69220352"
        },
        "context": {
          "reference": "urn:uuid:aed3dab6-227d-4de1-93e6-7488d6661515"
        },
        "period": {
          "start": "1963-08-09"
        },
        "addresses": [
          {
            "reference": "urn:uuid:be04a744-2d9e-4c40-a353-0510f6e979f9"
          }
        ],
        "goal": [
          {
            "reference": "urn:uuid:0167b972-465a-4047-9c0a-cef804548645"
          },
          {
            "reference": "urn:uuid:fb8a8498-41a1-4f1e-88eb-a2fc54d4100a"
          },
          {
            "reference": "urn:uuid:02cf1ed7-7f4f-4b9e-aea4-c7b9f48ed336"
          },
          {
            "reference": "urn:uuid:af3a5193-deb6-4ae2-a45e-ac2c2f0c2793"
          },
          {
            "reference": "urn:uuid:0889eeb5-7fa0-4d1d-bf45-bcd2b93498fc"
          }
        ],
        "activity": [
          {
            "detail": {
              "code": {
                "coding": [
                  {
                    "system": "http://snomed.info/sct",
                    "code": "160670007",
                    "display": "Diabetic diet"
                  }
                ]
              },
              "status": "in-progress"
            }
          },
          {
            "detail": {
              "code": {
                "coding": [
                  {
                    "system": "http://snomed.info/sct",
                    "code": "229065009",
                    "display": "Exercise therapy"
                  }
                ]
              },
              "status": "in-progress"
            }
          }
        ],
        "resourceType": "CarePlan"
      }
    },
    {
      "resource": {
        "status": "completed",
        "category": [
          {
            "coding": [
              {
                "system": "http://snomed.info/sct",
                "code": "134435003",
                "display": "Routine antenatal care"
              }
            ]
          }
        ],
        "subject": {
          "reference": "urn:uuid:85bc8c3a-470f-46b2-ba9f-4e3d69220352"
        },
        "context": {
          "reference": "urn:uuid:aed3dab6-227d-4de1-93e6-7488d6661515"
        },
        "period": {
          "start": "1963-12-13",
          "end": "1964-07-17"
        },
        "activity": [
          {
            "detail": {
              "code": {
                "coding": [
                  {
                    "system": "http://snomed.info/sct",
                    "code": "135892000",
                    "display": "Antenatal education"
                  }
                ]
              },
              "status": "completed"
            }
          },
          {
            "detail": {
              "code": {
                "coding": [
                  {
                    "system": "http://snomed.info/sct",
                    "code": "226060000",
                    "display": "Stress management"
                  }
                ]
              },
              "status": "completed"
            }
          },
          {
            "detail": {
              "code": {
                "coding": [
                  {
                    "system": "http://snomed.info/sct",
                    "code": "171054004",
                    "display": "Pregnancy diet education"
                  }
                ]
              },
              "status": "completed"
            }
          }
        ],
        "resourceType": "CarePlan"
      }
    },
    {
      "resource": {
        "status": "completed",
        "category": [
          {
            "coding": [
              {
                "system": "http://snomed.info/sct",
                "code": "134435003",
                "display": "Routine antenatal care"
              }
            ]
          }
        ],
        "subject": {
          "reference": "urn:uuid:85bc8c3a-470f-46b2-ba9f-4e3d69220352"
        },
        "context": {
          "reference": "urn:uuid:aed3dab6-227d-4de1-93e6-7488d6661515"
        },
        "period": {
          "start": "1966-06-03",
          "end": "1966-12-16"
        },
        "activity": [
          {
            "detail": {
              "code": {
                "coding": [
                  {
                    "system": "http://snomed.info/sct",
                    "code": "135892000",
                    "display": "Antenatal education"
                  }
                ]
              },
              "status": "completed"
            }
          },
          {
            "detail": {
              "code": {
                "coding": [
                  {
                    "system": "http://snomed.info/sct",
                    "code": "226060000",
                    "display": "Stress management"
                  }
                ]
              },
              "status": "completed"
            }
          },
          {
            "detail": {
              "code": {
                "coding": [
                  {
                    "system": "http://snomed.info/sct",
                    "code": "171054004",
                    "display": "Pregnancy diet education"
                  }
                ]
              },
              "status": "completed"
            }
          }
        ],
        "resourceType": "CarePlan"
      }
    },
    {
      "resource": {
        "status": "completed",
        "category": [
          {
            "coding": [
              {
                "system": "http://snomed.info/sct",
                "code": "134435003",
                "display": "Routine antenatal care"
              }
            ]
          }
        ],
        "subject": {
          "reference": "urn:uuid:85bc8c3a-470f-46b2-ba9f-4e3d69220352"
        },
        "context": {
          "reference": "urn:uuid:aed3dab6-227d-4de1-93e6-7488d6661515"
        },
        "period": {
          "start": "1969-12-19",
          "end": "1970-07-31"
        },
        "activity": [
          {
            "detail": {
              "code": {
                "coding": [
                  {
                    "system": "http://snomed.info/sct",
                    "code": "135892000",
                    "display": "Antenatal education"
                  }
                ]
              },
              "status": "completed"
            }
          },
          {
            "detail": {
              "code": {
                "coding": [
                  {
                    "system": "http://snomed.info/sct",
                    "code": "226060000",
                    "display": "Stress management"
                  }
                ]
              },
              "status": "completed"
            }
          },
          {
            "detail": {
              "code": {
                "coding": [
                  {
                    "system": "http://snomed.info/sct",
                    "code": "171054004",
                    "display": "Pregnancy diet education"
                  }
                ]
              },
              "status": "completed"
            }
          }
        ],
        "resourceType": "CarePlan"
      }
    },
    {
      "resource": {
        "status": "completed",
        "category": [
          {
            "coding": [
              {
                "system": "http://snomed.info/sct",
                "code": "134435003",
                "display": "Routine antenatal care"
              }
            ]
          }
        ],
        "subject": {
          "reference": "urn:uuid:85bc8c3a-470f-46b2-ba9f-4e3d69220352"
        },
        "context": {
          "reference": "urn:uuid:aed3dab6-227d-4de1-93e6-7488d6661515"
        },
        "period": {
          "start": "1970-11-13",
          "end": "1971-12-03"
        },
        "activity": [
          {
            "detail": {
              "code": {
                "coding": [
                  {
                    "system": "http://snomed.info/sct",
                    "code": "135892000",
                    "display": "Antenatal education"
                  }
                ]
              },
              "status": "completed"
            }
          },
          {
            "detail": {
              "code": {
                "coding": [
                  {
                    "system": "http://snomed.info/sct",
                    "code": "226060000",
                    "display": "Stress management"
                  }
                ]
              },
              "status": "completed"
            }
          },
          {
            "detail": {
              "code": {
                "coding": [
                  {
                    "system": "http://snomed.info/sct",
                    "code": "171054004",
                    "display": "Pregnancy diet education"
                  }
                ]
              },
              "status": "completed"
            }
          }
        ],
        "resourceType": "CarePlan"
      }
    },
    {
      "resource": {
        "status": "completed",
        "category": [
          {
            "coding": [
              {
                "system": "http://snomed.info/sct",
                "code": "134435003",
                "display": "Routine antenatal care"
              }
            ]
          }
        ],
        "subject": {
          "reference": "urn:uuid:85bc8c3a-470f-46b2-ba9f-4e3d69220352"
        },
        "context": {
          "reference": "urn:uuid:aed3dab6-227d-4de1-93e6-7488d6661515"
        },
        "period": {
          "start": "1971-04-23",
          "end": "1975-02-28"
        },
        "activity": [
          {
            "detail": {
              "code": {
                "coding": [
                  {
                    "system": "http://snomed.info/sct",
                    "code": "135892000",
                    "display": "Antenatal education"
                  }
                ]
              },
              "status": "completed"
            }
          },
          {
            "detail": {
              "code": {
                "coding": [
                  {
                    "system": "http://snomed.info/sct",
                    "code": "226060000",
                    "display": "Stress management"
                  }
                ]
              },
              "status": "completed"
            }
          },
          {
            "detail": {
              "code": {
                "coding": [
                  {
                    "system": "http://snomed.info/sct",
                    "code": "171054004",
                    "display": "Pregnancy diet education"
                  }
                ]
              },
              "status": "completed"
            }
          }
        ],
        "resourceType": "CarePlan"
      }
    },
    {
      "resource": {
        "status": "completed",
        "category": [
          {
            "coding": [
              {
                "system": "http://snomed.info/sct",
                "code": "134435003",
                "display": "Routine antenatal care"
              }
            ]
          }
        ],
        "subject": {
          "reference": "urn:uuid:85bc8c3a-470f-46b2-ba9f-4e3d69220352"
        },
        "context": {
          "reference": "urn:uuid:aed3dab6-227d-4de1-93e6-7488d6661515"
        },
        "period": {
          "start": "1974-07-26",
          "end": "1976-06-04"
        },
        "activity": [
          {
            "detail": {
              "code": {
                "coding": [
                  {
                    "system": "http://snomed.info/sct",
                    "code": "135892000",
                    "display": "Antenatal education"
                  }
                ]
              },
              "status": "completed"
            }
          },
          {
            "detail": {
              "code": {
                "coding": [
                  {
                    "system": "http://snomed.info/sct",
                    "code": "226060000",
                    "display": "Stress management"
                  }
                ]
              },
              "status": "completed"
            }
          },
          {
            "detail": {
              "code": {
                "coding": [
                  {
                    "system": "http://snomed.info/sct",
                    "code": "171054004",
                    "display": "Pregnancy diet education"
                  }
                ]
              },
              "status": "completed"
            }
          }
        ],
        "resourceType": "CarePlan"
      }
    },
    {
      "resource": {
        "status": "completed",
        "category": [
          {
            "coding": [
              {
                "system": "http://snomed.info/sct",
                "code": "134435003",
                "display": "Routine antenatal care"
              }
            ]
          }
        ],
        "subject": {
          "reference": "urn:uuid:85bc8c3a-470f-46b2-ba9f-4e3d69220352"
        },
        "context": {
          "reference": "urn:uuid:aed3dab6-227d-4de1-93e6-7488d6661515"
        },
        "period": {
          "start": "1975-11-14",
          "end": "1977-09-16"
        },
        "activity": [
          {
            "detail": {
              "code": {
                "coding": [
                  {
                    "system": "http://snomed.info/sct",
                    "code": "135892000",
                    "display": "Antenatal education"
                  }
                ]
              },
              "status": "completed"
            }
          },
          {
            "detail": {
              "code": {
                "coding": [
                  {
                    "system": "http://snomed.info/sct",
                    "code": "226060000",
                    "display": "Stress management"
                  }
                ]
              },
              "status": "completed"
            }
          },
          {
            "detail": {
              "code": {
                "coding": [
                  {
                    "system": "http://snomed.info/sct",
                    "code": "171054004",
                    "display": "Pregnancy diet education"
                  }
                ]
              },
              "status": "completed"
            }
          }
        ],
        "resourceType": "CarePlan"
      }
    },
    {
      "resource": {
        "status": "active",
        "category": [
          {
            "coding": [
              {
                "system": "http://snomed.info/sct",
                "code": "134435003",
                "display": "Routine antenatal care"
              }
            ]
          }
        ],
        "subject": {
          "reference": "urn:uuid:85bc8c3a-470f-46b2-ba9f-4e3d69220352"
        },
        "context": {
          "reference": "urn:uuid:aed3dab6-227d-4de1-93e6-7488d6661515"
        },
        "period": {
          "start": "1977-02-11"
        },
        "activity": [
          {
            "detail": {
              "code": {
                "coding": [
                  {
                    "system": "http://snomed.info/sct",
                    "code": "135892000",
                    "display": "Antenatal education"
                  }
                ]
              },
              "status": "in-progress"
            }
          },
          {
            "detail": {
              "code": {
                "coding": [
                  {
                    "system": "http://snomed.info/sct",
                    "code": "226060000",
                    "display": "Stress management"
                  }
                ]
              },
              "status": "in-progress"
            }
          },
          {
            "detail": {
              "code": {
                "coding": [
                  {
                    "system": "http://snomed.info/sct",
                    "code": "171054004",
                    "display": "Pregnancy diet education"
                  }
                ]
              },
              "status": "in-progress"
            }
          }
        ],
        "resourceType": "CarePlan"
      }
    },
    {
      "resource": {
        "status": "active",
        "category": [
          {
            "coding": [
              {
                "system": "http://snomed.info/sct",
                "code": "182964004",
                "display": "Terminal care"
              }
            ]
          }
        ],
        "subject": {
          "reference": "urn:uuid:85bc8c3a-470f-46b2-ba9f-4e3d69220352"
        },
        "context": {
          "reference": "urn:uuid:aed3dab6-227d-4de1-93e6-7488d6661515"
        },
        "period": {
          "start": "1990-03-20"
        },
        "addresses": [
          {
            "reference": "urn:uuid:84b7b4de-a990-4802-bef3-146d09a2da94"
          }
        ],
        "activity": [
          {
            "detail": {
              "code": {
                "coding": [
                  {
                    "system": "http://snomed.info/sct",
                    "code": "133918004",
                    "display": "Comfort measures"
                  }
                ]
              },
              "status": "in-progress"
            }
          },
          {
            "detail": {
              "code": {
                "coding": [
                  {
                    "system": "http://snomed.info/sct",
                    "code": "408957008",
                    "display": "Chronic pain control management"
                  }
                ]
              },
              "status": "in-progress"
            }
          },
          {
            "detail": {
              "code": {
                "coding": [
                  {
                    "system": "http://snomed.info/sct",
                    "code": "243072006",
                    "display": "Cancer education"
                  }
                ]
              },
              "status": "in-progress"
            }
          }
        ],
        "resourceType": "CarePlan"
      }
    },
    {
      "fullUrl": "urn:uuid:bda56f94-0e01-4225-9a26-6b6db33eb5df",
      "resource": {
        "id": "bda56f94-0e01-4225-9a26-6b6db33eb5df",
        "meta": {
          "profile": [
            "http://standardhealthrecord.org/fhir/StructureDefinition/shr-medication-Medication"
          ]
        },
        "code": {
          "coding": [
            {
              "system": "http://www.nlm.nih.gov/research/umls/rxnorm",
              "code": "860975",
              "display": "24 HR Metformin hydrochloride 500 MG Extended Release Oral Tablet"
            }
          ],
          "text": "24 HR Metformin hydrochloride 500 MG Extended Release Oral Tablet"
        },
        "resourceType": "Medication"
      }
    },
    {
      "fullUrl": "urn:uuid:73a7cd84-9fed-4e58-8513-1520fed65b39",
      "resource": {
        "id": "73a7cd84-9fed-4e58-8513-1520fed65b39",
        "meta": {
          "profile": [
            "http://standardhealthrecord.org/fhir/StructureDefinition/shr-medication-MedicationPrescription"
          ]
        },
        "extension": [
          {
            "url": "http://standardhealthrecord.org/fhir/StructureDefinition/shr-base-ActionCode-extension",
            "valueCodeableConcept": {
              "coding": [
                {
                  "system": "http://snomed.info/sct",
                  "code": "33633005",
                  "display": "Prescription of drug (procedure)"
                }
              ],
              "text": "Prescription of drug (procedure)"
            }
          }
        ],
        "status": "active",
        "intent": "order",
        "medicationReference": {
          "reference": "urn:uuid:bda56f94-0e01-4225-9a26-6b6db33eb5df"
        },
        "subject": {
          "reference": "urn:uuid:85bc8c3a-470f-46b2-ba9f-4e3d69220352"
        },
        "context": {
          "reference": "urn:uuid:aed3dab6-227d-4de1-93e6-7488d6661515"
        },
        "authoredOn": "1979-06-25",
        "reasonReference": [
          {
            "reference": "urn:uuid:be04a744-2d9e-4c40-a353-0510f6e979f9"
          }
        ],
        "resourceType": "MedicationRequest"
      }
    },
    {
      "fullUrl": "urn:uuid:46cdde4d-3034-4940-98cf-2cf0c0172765",
      "resource": {
        "id": "46cdde4d-3034-4940-98cf-2cf0c0172765",
        "meta": {
          "profile": [
            "http://standardhealthrecord.org/fhir/StructureDefinition/shr-observation-Observation"
          ]
        },
        "status": "final",
        "category": [
          {
            "coding": [
              {
                "system": "http://hl7.org/fhir/observation-category",
                "code": "survey"
              }
            ]
          }
        ],
        "code": {
          "coding": [
            {
              "system": "http://snomed.info/sct",
              "code": "273724008",
              "display": "Quality adjusted life years"
            }
          ],
          "text": "Quality adjusted life years"
        },
        "subject": {
          "reference": "urn:uuid:85bc8c3a-470f-46b2-ba9f-4e3d69220352"
        },
        "effectiveDateTime": "2017-10-06T22:39:41-04:00",
        "issued": "2017-10-06T22:39:41-04:00",
        "valueQuantity": {
          "value": 40.73409141792515,
          "unit": "years",
          "system": "http://unitsofmeasure.org/",
          "code": "years"
        },
        "resourceType": "Observation"
      }
    },
    {
      "fullUrl": "urn:uuid:61dd98f0-edaf-4f59-9daa-0aac8fdbf48f",
      "resource": {
        "id": "61dd98f0-edaf-4f59-9daa-0aac8fdbf48f",
        "meta": {
          "profile": [
            "http://standardhealthrecord.org/fhir/StructureDefinition/shr-observation-Observation"
          ]
        },
        "status": "final",
        "category": [
          {
            "coding": [
              {
                "system": "http://hl7.org/fhir/observation-category",
                "code": "survey"
              }
            ]
          }
        ],
        "code": {
          "coding": [
            {
              "system": "http://snomed.info/sct",
              "code": "273421001",
              "display": "Disability rating scale"
            }
          ],
          "text": "Disability rating scale"
        },
        "subject": {
          "reference": "urn:uuid:85bc8c3a-470f-46b2-ba9f-4e3d69220352"
        },
        "effectiveDateTime": "2017-10-06T22:39:41-04:00",
        "issued": "2017-10-06T22:39:41-04:00",
        "valueQuantity": {
          "value": 46.91590858207485,
          "unit": "years",
          "system": "http://unitsofmeasure.org/",
          "code": "years"
        },
        "resourceType": "Observation"
      }
    }
  ],
  "resourceType": "Bundle"
}